sar_logic.v
module sar_logic(
	input clk,
	input rst,
	input cnvst,
	input cmp_out,
	output reg [7:0] sar, // digital output
	output reg eoc, // end of conversion
	output reg cmp_clk, // comparator clock

	output reg s_clk, // bootstrap switch clock

	output reg [8:0] fine_sca1_top,
	output reg [8:0] fine_sca1_btm,
	output reg [8:0] fine_sca2_top,
	output reg [8:0] fine_sca2_btm
	);
	
	parameter S_start 	= 3'd0;
	parameter S_sample	= 3'd1;
	parameter S_compare	= 3'd2;
	parameter S_decide	= 3'd3;

	reg [3:0] state;
	reg [3:0] b;

	always @(posedge clk) begin //state transitions
		if (rst) 
			state <= S_start;
		else
			case(state)
				S_start:
					if(cnvst)
						state <= S_sample;
					else 
						state <= S_start;
				S_sample:
					state <= S_compare;
				S_compare:
					state <= S_decide;
				S_decide:
					if(b==0)
						state <= S_start;
					else
						state <= S_compare;
			endcase
	end


	always @(posedge clk) begin //eoc
		if (rst) 
			// reset
			eoc <= 0;
		else 
			if (b == 0 && state == S_decide) 
				eoc <= 1;
			else
				eoc <= 0;
	end

	always @(posedge clk) begin //b
		if (rst)
			// reset
			b <= 0;
		else 
			case(state)
				S_sample:
					b <= 4'd7;
				S_decide:
					if(b)
						b <= b - 1; 
			endcase
	end

	always @(posedge clk) begin //s_clk
		if (rst) 
			// reset
			s_clk <= 0;
		else 
			if (state == S_sample) 
				s_clk <= 1;
			else
				s_clk <= 0;
	end

	always @(posedge clk) begin //cmp_clk
		if (rst) 
			// reset
			cmp_clk <= 0;
		else 
			if (state == S_compare) 
				cmp_clk <= 1;
			else
				cmp_clk <= 0;
	end

	always @(posedge clk) begin //sar
		if (rst) begin
			// reset
			sar <= 0;
		end
		else
			case(state)
				S_start:
					sar[4'd7] <= 1;
				S_decide: begin
					if(cmp_out == 0)
						sar[b] <= 0;
					if(b)
						sar[b-1] <= 1;
				end
			endcase
	end

	always @(posedge clk) begin //DAC_switch_control
		if (rst) begin
			// reset
			fine_sca1_top[8:0] <= 9'b111111111;
			fine_sca1_btm[8:0] <= 0;
			fine_sca2_top[8:0] <= 9'b111111111;
			fine_sca2_btm[8:0] <= 0;
		end
		else
			case(state)
				S_start: begin
					fine_sca1_top[8:0] <= 9'b111111111;
					fine_sca1_btm[8:0] <= 0;
					fine_sca2_top[8:0] <= 9'b111111111;
					fine_sca2_btm[8:0] <= 0;
				end
				/*S_decide: begin
					if(cmp_out == 0)
						case(b)
						endcase
					else
						case(b)
						endcase
				end*/
			endcase
		
	end

endmodule

sar_logic_tb.v
`timescale 1ns/100ps

module sar_logic_tb;
	reg clk;
	reg rst;
	reg cnvst;
	reg cmp_out;
	wire [7:0] sar;
	wire eoc;
	wire cmp_clk;
	wire s_clk;

	wire [8:0] fine_sca1_top;
	wire [8:0] fine_sca1_btm;
	wire [8:0] fine_sca2_top;
	wire [8:0] fine_sca2_btm;


	sar_logic test(clk, rst, cnvst, cmp_out, sar, eoc, cmp_clk, s_clk, fine_sca1_top, fine_sca1_btm, fine_sca2_top, fine_sca2_btm);

	always #5 clk = !clk;

	initial begin

		$dumpfile("sar_logic.vcd");
		$dumpvars(0, sar_logic_tb);

		clk = 0;
		rst = 1;
		cnvst = 0;
		cmp_out = 0;

		#30

		rst = 0;
		cmp_out = 0;
		cnvst = 1;

		#20

		cnvst = 0;

		#300

		

		$finish;

	end
endmodule

sar_logic.vcd
$date
	Sun Feb 18 02:07:52 2018
$end
$version
	Icarus Verilog
$end
$timescale
	100ps
$end
$scope module sar_logic_tb $end
$var wire 8 ! sar [7:0] $end
$var wire 1 " s_clk $end
$var wire 9 # fine_sca2_top [8:0] $end
$var wire 9 $ fine_sca2_btm [8:0] $end
$var wire 9 % fine_sca1_top [8:0] $end
$var wire 9 & fine_sca1_btm [8:0] $end
$var wire 1 ' eoc $end
$var wire 1 ( cmp_clk $end
$var reg 1 ) clk $end
$var reg 1 * cmp_out $end
$var reg 1 + cnvst $end
$var reg 1 , rst $end
$scope module test $end
$var wire 1 ) clk $end
$var wire 1 * cmp_out $end
$var wire 1 + cnvst $end
$var wire 1 , rst $end
$var reg 4 - b [3:0] $end
$var reg 1 ( cmp_clk $end
$var reg 1 ' eoc $end
$var reg 9 . fine_sca1_btm [8:0] $end
$var reg 9 / fine_sca1_top [8:0] $end
$var reg 9 0 fine_sca2_btm [8:0] $end
$var reg 9 1 fine_sca2_top [8:0] $end
$var reg 1 " s_clk $end
$var reg 8 2 sar [7:0] $end
$var reg 4 3 state [3:0] $end
$upscope $end
$upscope $end
$enddefinitions $end
#0
$dumpvars
bx 3
bx 2
bx 1
bx 0
bx /
bx .
bx -
1,
0+
0*
0)
x(
x'
bx &
bx %
bx $
bx #
x"
bx !
$end
#50
b0 3
0'
b0 -
0"
0(
b0 !
b0 2
b0 $
b0 0
b111111111 #
b111111111 1
b0 &
b0 .
b111111111 %
b111111111 /
1)
#100
0)
#150
1)
#200
0)
#250
1)
#300
0)
1+
0,
#350
b10000000 !
b10000000 2
b1 3
1)
#400
0)
#450
b10 3
b111 -
1"
1)
#500
0)
0+
#550
1(
0"
b11 3
1)
#600
0)
#650
b10 3
b110 -
0(
b1000000 !
b1000000 2
1)
#700
0)
#750
1(
b11 3
1)
#800
0)
#850
b10 3
b101 -
0(
b100000 !
b100000 2
1)
#900
0)
#950
1(
b11 3
1)
#1000
0)
#1050
b10 3
b100 -
0(
b10000 !
b10000 2
1)
#1100
0)
#1150
1(
b11 3
1)
#1200
0)
#1250
b10 3
b11 -
0(
b1000 !
b1000 2
1)
#1300
0)
#1350
1(
b11 3
1)
#1400
0)
#1450
b10 3
b10 -
0(
b100 !
b100 2
1)
#1500
0)
#1550
1(
b11 3
1)
#1600
0)
#1650
b10 3
b1 -
0(
b10 !
b10 2
1)
#1700
0)
#1750
1(
b11 3
1)
#1800
0)
#1850
b10 3
b0 -
0(
b1 !
b1 2
1)
#1900
0)
#1950
1(
b11 3
1)
#2000
0)
#2050
b0 3
1'
0(
b0 !
b0 2
1)
#2100
0)
#2150
b10000000 !
b10000000 2
0'
1)
