sar_logic_CS_10bit.v
module sar_logic_CS(
	input clk,
	input rst,
	input cnvst,
	input cmp_out,
	output reg [9:0] sar, // digital output
	output reg eoc, // end of conversion
	output reg cmp_clk, // comparator clock

	output reg s_clk, // bootstrap switch clock
	output reg [19:0] fine_btm,
	output reg fine_switch_drain,

	//INVERTED OUTPUTS
	output s_clk_not,
	output [19:0] fine_btm_not,
	output fine_switch_drain_not
	);
	
	// 256 128 64 32 16 8  4  2  1  1  256 128 64 32 16 8 4 2 1 1
	//  19  18 17 16 15 14 13 12 11 10   9   8  7  6  5 4 3 2 1 0 
	parameter S_wait		= 3'd0;
	parameter S_drain 	= 3'd1;
	parameter S_comprst	= 3'd2;
	parameter S_decide	= 3'd3;

	assign s_clk_not = ~s_clk;
	assign fine_btm_not = ~fine_btm;
	assign fine_switch_drain_not = ~fine_switch_drain;

	reg [2:0] state;
	reg [1:0] drain;
	reg [3:0] b;

	reg fine_up; // 1 if SCA2 has upper bound voltage

	always @(posedge clk) begin //state transitions
		if (rst) 
			state <= S_wait;
		else
			case(state)
				S_wait:
					if(cnvst)
						state <= S_drain;
					else 
						state <= S_wait;
				S_drain:
					if(drain)
						state <= S_drain;
					else
						state <= S_comprst;
				S_comprst:
					state <= S_decide;
				S_decide:
					if(b==0)
						state <= S_wait;
					else
						state <= S_comprst;

			endcase
	end


	always @(posedge clk) begin //eoc
		if (rst) 
			// reset
			eoc <= 0;
		else 
			if (b == 0 && state == S_decide) 
				eoc <= 1;
			else
				eoc <= 0;
	end


	always @(posedge clk) begin //b
		if (rst)
			// reset
			b <= 0;
		else 
			case(state)
				S_wait:
					b <= 4'd9;
				S_decide:
					if(b)
						b <= b - 1;
			endcase
	end

	always @(*) begin //s_clk
		if (rst) 
			// reset
			s_clk <= 1;
		else 
			if (state == S_wait) 
				s_clk <= 1;
			else
				s_clk <= 0;
	end

	always @(posedge clk) begin //cmp_clk
		if (rst) 
			// reset
			cmp_clk <= 0;
		else 
			if (state == S_comprst) 
				cmp_clk <= 1;
			else
				cmp_clk <= 0;
	end


	always @(posedge clk) begin //drain
		if (rst) 
			// reset
			drain <= 1;
		else 
			if (state == S_drain && drain)
				drain <= drain - 1;
			else if (state == S_wait)
				drain <= 2;
	end

	always @(posedge clk) begin //sar
		if (rst) begin
			// reset
			sar <= 0;
		end
		else
			case(state)
				S_wait:
					sar <= 10'b1000000000;
				S_decide: begin
					if(cmp_out == 0)
						sar[b] <= 0;
					if(b)
						sar[b-1] <= 1;
				end
				
			endcase
	end


	always @(posedge clk) begin //DAC_switch_control
		if (rst) begin
			// reset
			fine_btm <= 20'd0;
			fine_switch_drain <= 0;
		end
		else
			case(state)
				S_wait: begin
					fine_btm <= 20'd0;
					fine_switch_drain <= 0;
				end
				S_drain:
					case(drain)
						2'd2:
							fine_switch_drain <= 1;
						2'd1:
							fine_switch_drain <= 0;
						2'd0: begin
							fine_switch_drain <= 0;
							fine_btm <= 20'b11111111110000000000;
							end
						endcase
				S_decide:
					if(cmp_out) begin
						fine_btm[b] <= 1;
					end		

					else begin
						fine_btm[b+10] <= 0;
					end

			endcase
		
	end

endmodule

sar_logic_CS_10bit_tb.v
`timescale 1ns/100ps

module sar_logic_CS_10bit_tb;
	reg clk;
	reg rst;
	reg cnvst;
	reg cmp_out;
	wire [9:0] sar; // digital output
	wire eoc; // end of conversion
	wire cmp_clk; // comparator clock

	wire s_clk; // bootstrap switch clock
	wire [19:0] fine_btm;
	wire fine_switch_drain;

	//INVERTED OUTPUTS
	wire s_clk_not;
	wire [19:0] fine_btm_not;
	wire fine_switch_drain_not;


	sar_logic_CS test(clk, rst, cnvst, cmp_out, sar, eoc, cmp_clk, s_clk, fine_btm, fine_switch_drain, s_clk_not, fine_btm_not, fine_switch_drain_not);

	always #5 clk = !clk;

	initial begin

		$dumpfile("sar_logic_CS_10bit.vcd");
		$dumpvars(0, sar_logic_CS_10bit_tb);

		clk = 0;
		rst = 1;
		cnvst = 0;
		cmp_out = 1;

		#30

		rst = 0;
		cmp_out = 1;
		cnvst = 1;

		#20

		cnvst = 1;

		#300

		

		$finish;

	end
endmodule

sar_logic_CS_10bit.vcd
$date
	Fri Mar 09 14:17:10 2018
$end
$version
	Icarus Verilog
$end
$timescale
	100ps
$end
$scope module sar_logic_CS_10bit_tb $end
$var wire 10 ! sar [9:0] $end
$var wire 1 " s_clk_not $end
$var wire 1 # s_clk $end
$var wire 1 $ fine_switch_drain_not $end
$var wire 1 % fine_switch_drain $end
$var wire 20 & fine_btm_not [19:0] $end
$var wire 20 ' fine_btm [19:0] $end
$var wire 1 ( eoc $end
$var wire 1 ) cmp_clk $end
$var reg 1 * clk $end
$var reg 1 + cmp_out $end
$var reg 1 , cnvst $end
$var reg 1 - rst $end
$scope module test $end
$var wire 1 * clk $end
$var wire 1 + cmp_out $end
$var wire 1 , cnvst $end
$var wire 20 . fine_btm_not [19:0] $end
$var wire 1 $ fine_switch_drain_not $end
$var wire 1 - rst $end
$var wire 1 " s_clk_not $end
$var reg 4 / b [3:0] $end
$var reg 1 ) cmp_clk $end
$var reg 2 0 drain [1:0] $end
$var reg 1 ( eoc $end
$var reg 20 1 fine_btm [19:0] $end
$var reg 1 % fine_switch_drain $end
$var reg 1 # s_clk $end
$var reg 10 2 sar [9:0] $end
$var reg 3 3 state [2:0] $end
$upscope $end
$upscope $end
$enddefinitions $end
#0
$dumpvars
bx 3
bx 2
bx 1
bx 0
bx /
bx .
1-
0,
1+
0*
x)
x(
bx '
bx &
x%
x$
1#
0"
bx !
$end
#50
1$
b11111111111111111111 &
b11111111111111111111 .
b0 3
0(
b0 /
0)
b1 0
b0 !
b0 2
0%
b0 '
b0 1
1*
#100
0*
#150
1*
#200
0*
#250
1*
#300
0*
1,
0-
#350
1"
0#
b1000000000 !
b1000000000 2
b10 0
b1001 /
b1 3
1*
#400
0*
#450
0$
b1 0
1%
1*
#500
0*
#550
1$
0%
b0 0
1*
#600
0*
#650
b1111111111 &
b1111111111 .
b10 3
b11111111110000000000 '
b11111111110000000000 1
1*
#700
0*
#750
1)
b11 3
1*
#800
0*
#850
b111111111 &
b111111111 .
b10 3
b1000 /
0)
b1100000000 !
b1100000000 2
b11111111111000000000 '
b11111111111000000000 1
1*
#900
0*
#950
1)
b11 3
1*
#1000
0*
#1050
b11111111 &
b11111111 .
b10 3
b111 /
0)
b1110000000 !
b1110000000 2
b11111111111100000000 '
b11111111111100000000 1
1*
#1100
0*
#1150
1)
b11 3
1*
#1200
0*
#1250
b1111111 &
b1111111 .
b10 3
b110 /
0)
b1111000000 !
b1111000000 2
b11111111111110000000 '
b11111111111110000000 1
1*
#1300
0*
#1350
1)
b11 3
1*
#1400
0*
#1450
b111111 &
b111111 .
b10 3
b101 /
0)
b1111100000 !
b1111100000 2
b11111111111111000000 '
b11111111111111000000 1
1*
#1500
0*
#1550
1)
b11 3
1*
#1600
0*
#1650
b11111 &
b11111 .
b10 3
b100 /
0)
b1111110000 !
b1111110000 2
b11111111111111100000 '
b11111111111111100000 1
1*
#1700
0*
#1750
1)
b11 3
1*
#1800
0*
#1850
b1111 &
b1111 .
b10 3
b11 /
0)
b1111111000 !
b1111111000 2
b11111111111111110000 '
b11111111111111110000 1
1*
#1900
0*
#1950
1)
b11 3
1*
#2000
0*
#2050
b111 &
b111 .
b10 3
b10 /
0)
b1111111100 !
b1111111100 2
b11111111111111111000 '
b11111111111111111000 1
1*
#2100
0*
#2150
1)
b11 3
1*
#2200
0*
#2250
b11 &
b11 .
b10 3
b1 /
0)
b1111111110 !
b1111111110 2
b11111111111111111100 '
b11111111111111111100 1
1*
#2300
0*
#2350
1)
b11 3
1*
#2400
0*
#2450
b1 &
b1 .
b10 3
b0 /
0)
b1111111111 !
b1111111111 2
b11111111111111111110 '
b11111111111111111110 1
1*
#2500
0*
#2550
1)
b11 3
1*
#2600
0*
#2650
0"
1#
b0 &
b0 .
b0 3
1(
0)
b11111111111111111111 '
b11111111111111111111 1
1*
#2700
0*
#2750
1"
0#
b11111111111111111111 &
b11111111111111111111 .
b0 '
b0 1
b1000000000 !
b1000000000 2
b10 0
b1001 /
0(
b1 3
1*
#2800
0*
#2850
0$
b1 0
1%
1*
#2900
0*
#2950
1$
0%
b0 0
1*
#3000
0*
#3050
b1111111111 &
b1111111111 .
b10 3
b11111111110000000000 '
b11111111110000000000 1
1*
#3100
0*
#3150
1)
b11 3
1*
#3200
0*
#3250
b111111111 &
b111111111 .
b10 3
b1000 /
0)
b1100000000 !
b1100000000 2
b11111111111000000000 '
b11111111111000000000 1
1*
#3300
0*
#3350
1)
b11 3
1*
#3400
0*
#3450
b11111111 &
b11111111 .
b10 3
b111 /
0)
b1110000000 !
b1110000000 2
b11111111111100000000 '
b11111111111100000000 1
1*
