sar_logic.v
module sar_logic(
	input clk,
	input rst,
	input cnvst,
	input cmp_out,
	output reg [7:0] sar, // digital output
	output reg eoc, // end of conversion
	output reg cmp_clk, // comparator clock

	output reg s_clk, // bootstrap switch clock

	output reg [8:0] fine_sca1_top,
	output reg [8:0] fine_sca1_btm,
	output reg [8:0] fine_sca2_top,
	output reg [8:0] fine_sca2_btm,
	output reg fine_switch_S
	);
	
	parameter S_wait		= 3'd0;
	parameter S_comprst	= 3'd1;
	parameter S_coarse	= 3'd2;
	parameter S_bndset	= 3'd3;
	parameter S_fine		= 3'd4;

	reg [8:0] fine_sca1_top_wait;
	reg [8:0] fine_sca2_top_wait;

	reg [3:0] state;
	reg [3:0] b_coarse;
	reg [3:0] b_fine;
	reg bndset;

	reg fine_up; // 1 if SCA2 has upper bound voltage

	always @(posedge clk) begin //state transitions
		if (rst) 
			state <= S_wait;
		else
			case(state)
				S_wait:
					if(cnvst)
						state <= S_comprst;
					else 
						state <= S_wait;
				S_comprst:
					if(b_coarse)
						state <= S_coarse;
					else if(bndset)
						state <= S_bndset;
					else
						state <= S_fine;
				S_coarse:
					if(b_coarse==0)
						state <= S_bndset;
					else
						state <= S_comprst;
				S_bndset:
					if(bndset)
						state <= S_bndset;
					else
						state <= S_comprst;
				S_fine:
					if(b_fine==0)
						state <= S_wait;
					else
						state <= S_comprst;

			endcase
	end


	always @(posedge clk) begin //eoc
		if (rst) 
			// reset
			eoc <= 0;
		else 
			if (b_fine == 0 && state == S_fine) 
				eoc <= 1;
			else
				eoc <= 0;
	end

	always @(posedge clk) begin //bndset
		if (rst)
			// reset
			bndset <= 1;
		else 
			case(state)
				S_wait:
					bndset <= 1;
				S_bndset:
					bndset <= 0;
			endcase
	end

	always @(posedge clk) begin //b_coarse
		if (rst)
			// reset
			b_coarse <= 0;
		else 
			case(state)
				S_wait:
					b_coarse <= 4'd3;
				S_coarse:
					if(b_coarse)
						b_coarse <= b_coarse - 1;
			endcase
	end

	always @(posedge clk) begin //b_fine
		if (rst)
			// reset
			b_fine <= 0;
		else 
			case(state)
				S_wait:
					b_fine <= 4'd3;
				S_fine:
					if(b_fine)
						b_fine <= b_fine - 1;
			endcase
	end

	always @(*) begin //s_clk
		if (rst) 
			// reset
			s_clk <= 1;
		else 
			if (state == S_wait) 
				s_clk <= 1;
			else
				s_clk <= 0;
	end

	always @(posedge clk) begin //cmp_clk
		if (rst) 
			// reset
			cmp_clk <= 0;
		else 
			if (state == S_comprst) 
				cmp_clk <= 1;
			else
				cmp_clk <= 0;
	end

	always @(posedge clk) begin //fine_up
		if (rst) 
			// reset
			fine_up <= 0;
		else 
			if (state == S_bndset && bndset && cmp_out) 
				fine_up <= 1;
	end

	always @(posedge clk) begin //sar
		if (rst) begin
			// reset
			sar <= 0;
		end
		else
			case(state)
				S_wait:
					sar[4'd7] <= 1;
				S_coarse: begin
					if(cmp_out == 0)
						sar[b_coarse+4'd4] <= 0;
					if(b_coarse)
						sar[b_coarse+4'd3] <= 1;
				end
				S_bndset:
					sar[4'd3] <= 1;
				S_fine: begin
					if(cmp_out == 0)
						sar[b_fine] <= 0;
					if(b_fine)
						sar[b_fine-1] <= 1;
				end
			endcase
	end

	always @(posedge clk) begin //DAC_switch_control
		if (rst) begin
			// reset
			fine_sca1_top <= 9'b111111111;
			fine_sca1_btm <= 9'b111100000;
			fine_sca2_top <= 9'b111111111;
			fine_sca2_btm <= 9'b111100000;
			fine_switch_S <= 0;
		end
		else
			case(state)
				S_wait: begin
					fine_sca1_top <= 9'b111111111;
					fine_sca1_btm <= 9'b111100000;
					fine_sca2_top <= 9'b111111111;
					fine_sca2_btm <= 9'b000000000;
					fine_switch_S <= 0;
					fine_sca1_top_wait <= 9'b000000000;
					fine_sca2_top_wait <= 9'b000000000;
				end
				S_coarse:
					case(b_coarse)
						4'd3:
							if(cmp_out) begin
								fine_sca1_btm[4:3] <= 2'b11;
							end		

							else begin
								fine_sca1_btm[8] <= 0;
							end
						4'd2:
							if(cmp_out) begin
								fine_sca1_btm[2] <= 1;
							end		
											
							else begin
								fine_sca1_btm[7] <= 0;
							end
						4'd1:
							if(cmp_out) begin
								fine_sca1_btm[1] <= 1;
							end		
											
							else begin
								fine_sca1_btm[6] <= 0;
							end
						4'd0:
							if(cmp_out) begin
								fine_sca1_btm[4:3] <= 2'b11;
							end		
											
							else begin
								fine_sca1_btm[4:3] <= 2'b11;
							end
					endcase

				S_bndset:
					case(bndset)
						1:
							if(cmp_out) begin
								fine_sca2_btm[8:1] <= fine_sca1_btm[8:1];
								fine_sca2_btm[0] <= 1;
							end		
											
							else begin
								fine_sca2_btm[8:6] <= fine_sca1_btm[8:6];
								fine_sca2_btm[5] <= 0;
								fine_sca2_btm[4:0] <= fine_sca1_btm[4:0];
							end
						0: begin
							fine_sca1_top_wait <= 9'b000000010;
							fine_sca2_top_wait <= 9'b000000010;
							fine_sca1_top <= 9'b000000010;
							fine_sca2_top <= 9'b000000010;
							fine_switch_S <= 1;
						end
					endcase

				S_fine:
					case(b_fine)
						4'd3:
							if( (cmp_out && fine_up == 0) || (cmp_out == 0 && fine_up) ) begin
								fine_sca1_top_wait[3:2] <= 2'b11;
								fine_sca1_top_wait[8] <= 1;
								fine_sca1_top[2] <= 1;
							end		
											
							else begin
								fine_sca2_top_wait[3:2] <= 2'b11;
								fine_sca2_top_wait[8] <= 1;
								fine_sca2_top[2] <= 1;
							end
						4'd2:
							if( (cmp_out && fine_up == 0) || (cmp_out == 0 && fine_up) ) begin
								fine_sca1_top_wait[7] <= 1;
								fine_sca1_top_wait[4] <= 1;
								fine_sca1_top[3] <= fine_sca1_top_wait[3];
								fine_sca1_top[4] <= 1;
							end		
											
							else begin
								fine_sca2_top_wait[7] <= 1;
								fine_sca2_top_wait[4] <= 1;
								fine_sca2_top[3] <= fine_sca2_top_wait[3];
								fine_sca2_top[4] <= 1;							
							end
						4'd1:
							if( (cmp_out && fine_up == 0) || (cmp_out == 0 && fine_up) ) begin
								fine_sca1_top_wait[6:5] <= 2'b11;
								fine_sca1_top[8:7] <= fine_sca1_top_wait[8:7];
								fine_sca1_top[6:5] <= 2'b11;
							end		
											
							else begin
								fine_sca2_top_wait[6:5] <= 2'b11;
								fine_sca2_top[8:7] <= fine_sca2_top_wait[8:7];
								fine_sca2_top[6:5] <= 2'b11;
							end
						// 4'd0:
						// 	if( (cmp_out && fine_up == 0) || (cmp_out == 0 && fine_up) ) begin
						// 		fine_sca1_top[6:5] <= 2'b11;
						// 		fine_sca1_top[0] <= 1;
						// 	end		
											
						// 	else begin
						// 		fine_sca2_top[6:5] <= 2'b11;
						// 		fine_sca2_top[0] <= 1;
						// 	end

					endcase				
			endcase
		
	end

endmodule

sar_logic_tb.v
`timescale 1ns/100ps

module sar_logic_tb;
	reg clk;
	reg rst;
	reg cnvst;
	reg cmp_out;
	wire [7:0] sar;
	wire eoc;
	wire cmp_clk;
	wire s_clk;

	wire [8:0] fine_sca1_top;
	wire [8:0] fine_sca1_btm;
	wire [8:0] fine_sca2_top;
	wire [8:0] fine_sca2_btm;
	wire fine_switch_S;


	sar_logic test(clk, rst, cnvst, cmp_out, sar, eoc, cmp_clk, s_clk, fine_sca1_top, fine_sca1_btm, fine_sca2_top, fine_sca2_btm, fine_switch_S);

	always #5 clk = !clk;

	initial begin

		$dumpfile("sar_logic.vcd");
		$dumpvars(0, sar_logic_tb);

		clk = 0;
		rst = 1;
		cnvst = 0;
		cmp_out = 0;

		#30

		rst = 0;
		cmp_out = 0;
		cnvst = 1;

		#20

		cnvst = 0;

		#300

		

		$finish;

	end
endmodule

sar_logic.vcd
$date
	Mon Feb 19 19:34:27 2018
$end
$version
	Icarus Verilog
$end
$timescale
	100ps
$end
$scope module sar_logic_tb $end
$var wire 8 ! sar [7:0] $end
$var wire 1 " s_clk $end
$var wire 1 # fine_switch_S $end
$var wire 9 $ fine_sca2_top [8:0] $end
$var wire 9 % fine_sca2_btm [8:0] $end
$var wire 9 & fine_sca1_top [8:0] $end
$var wire 9 ' fine_sca1_btm [8:0] $end
$var wire 1 ( eoc $end
$var wire 1 ) cmp_clk $end
$var reg 1 * clk $end
$var reg 1 + cmp_out $end
$var reg 1 , cnvst $end
$var reg 1 - rst $end
$scope module test $end
$var wire 1 * clk $end
$var wire 1 + cmp_out $end
$var wire 1 , cnvst $end
$var wire 1 - rst $end
$var reg 4 . b_coarse [3:0] $end
$var reg 4 / b_fine [3:0] $end
$var reg 1 0 bndset $end
$var reg 1 ) cmp_clk $end
$var reg 1 ( eoc $end
$var reg 9 1 fine_sca1_btm [8:0] $end
$var reg 9 2 fine_sca1_top [8:0] $end
$var reg 9 3 fine_sca1_top_wait [8:0] $end
$var reg 9 4 fine_sca2_btm [8:0] $end
$var reg 9 5 fine_sca2_top [8:0] $end
$var reg 9 6 fine_sca2_top_wait [8:0] $end
$var reg 1 # fine_switch_S $end
$var reg 1 7 fine_up $end
$var reg 1 " s_clk $end
$var reg 8 8 sar [7:0] $end
$var reg 4 9 state [3:0] $end
$upscope $end
$upscope $end
$enddefinitions $end
#0
$dumpvars
bx 9
bx 8
x7
bx 6
bx 5
bx 4
bx 3
bx 2
bx 1
x0
bx /
bx .
1-
0,
0+
0*
x)
x(
bx '
bx &
bx %
bx $
x#
1"
bx !
$end
#50
b0 9
0(
10
b0 .
b0 /
0)
07
b0 !
b0 8
0#
b111100000 %
b111100000 4
b111111111 $
b111111111 5
b111100000 '
b111100000 1
b111111111 &
b111111111 2
1*
#100
0*
#150
1*
#200
0*
#250
1*
#300
0*
1,
0-
#350
0"
b0 6
b0 3
b0 %
b0 4
b10000000 !
b10000000 8
b11 /
b11 .
b1 9
1*
#400
0*
#450
b10 9
1)
1*
#500
0*
0,
#550
b11100000 '
b11100000 1
b1000000 !
b1000000 8
0)
b10 .
b1 9
1*
#600
0*
#650
b10 9
1)
1*
#700
0*
#750
b1100000 '
b1100000 1
b100000 !
b100000 8
0)
b1 .
b1 9
1*
#800
0*
#850
b10 9
1)
1*
#900
0*
#950
b100000 '
b100000 1
b10000 !
b10000 8
0)
b0 .
b1 9
1*
#1000
0*
#1050
b11 9
1)
1*
#1100
0*
#1150
b11000 !
b11000 8
0)
00
1*
#1200
0*
#1250
b1 9
1#
b10 $
b10 5
b10 &
b10 2
b10 6
b10 3
1*
#1300
0*
#1350
1)
b100 9
1*
#1400
0*
#1450
b1 9
b10 /
0)
b10100 !
b10100 8
b110 $
b110 5
b100001110 6
1*
#1500
0*
#1550
1)
b100 9
1*
#1600
0*
#1650
b1 9
b1 /
0)
b10010 !
b10010 8
b11110 $
b11110 5
b110011110 6
1*
#1700
0*
#1750
1)
b100 9
1*
#1800
0*
#1850
b1 9
b0 /
0)
b10001 !
b10001 8
b111111110 $
b111111110 5
b111111110 6
1*
#1900
0*
#1950
1)
b100 9
1*
#2000
0*
#2050
1"
b0 9
1(
0)
b10000 !
b10000 8
1*
#2100
0*
#2150
b0 6
b0 3
0#
b111111111 $
b111111111 5
b111100000 '
b111100000 1
b111111111 &
b111111111 2
b10010000 !
b10010000 8
b11 /
b11 .
10
0(
1*
