sar_logic_TSCS_10bit_k7.v
module sar_logic_TSCS_10bit_k7(
	input clk,
	input rst,
	input cnvst,
	input coarse_cmp_out,
	input fine_cmp_out,
	output reg [9:0] sar, // digital output
	output reg eoc, // end of conversion
	output reg coarse_cmp_clk, // comparator clock
	output reg fine_cmp_clk,

	output reg s_clk, // bootstrap switch clock

	output reg [8:0] coarse_sca1_top,
	output reg [8:0] coarse_sca1_btm,
	output reg [8:0] coarse_sca2_top,
	output reg [8:0] coarse_sca2_btm,
	output reg coarse_switch_S,
	output reg coarse_switch_drain,

	output reg [12:0] fine_sca1_top,
	output reg [12:0] fine_sca1_btm,
	output reg [12:0] fine_sca2_top,
	output reg [12:0] fine_sca2_btm,
	output reg fine_switch_S,
	output reg fine_switch_drain,

	//INVERTED OUTPUTS
	output s_clk_not,
	output [8:0] coarse_sca1_top_not,
	output [8:0] coarse_sca1_btm_not,
	output [8:0] coarse_sca2_top_not,
	output [8:0] coarse_sca2_btm_not,
	output coarse_switch_S_not,
	output coarse_switch_drain_not,

	output [12:0] fine_sca1_top_not,
	output [12:0] fine_sca1_btm_not,
	output [12:0] fine_sca2_top_not,
	output [12:0] fine_sca2_btm_not,
	output fine_switch_S_not,
	output fine_switch_drain_not
	);
	
	parameter S_wait						= 4'd0;
	parameter S_coarse_drain 		= 4'd1;
	parameter S_coarse_comprst	= 4'd2;
	parameter S_coarse_c				= 4'd3;
	parameter S_coarse_bndset		= 4'd4;
	parameter S_coarse_swtop		= 4'd5;
	parameter S_coarse_f				= 4'd6;
	parameter S_detskip					= 4'd7;
	parameter S_fine_comprst		= 4'd8;
	parameter S_fine_c					= 4'd9;
	parameter S_fine_swtop			= 4'd10;
	parameter S_fine_f					= 4'd11;

	assign s_clk_not = ~s_clk;
	assign coarse_sca1_top_not = ~coarse_sca1_top;
	assign coarse_sca1_btm_not = ~coarse_sca1_btm;
	assign coarse_sca2_top_not = ~coarse_sca2_top;
	assign coarse_sca2_btm_not = ~coarse_sca2_btm;
	assign coarse_switch_S_not = ~coarse_switch_S;
	assign coarse_switch_drain_not = ~coarse_switch_drain;
	assign fine_sca1_top_not = ~fine_sca1_top;
	assign fine_sca1_btm_not = ~fine_sca1_btm;
	assign fine_sca2_top_not = ~fine_sca2_top;
	assign fine_sca2_btm_not = ~fine_sca2_btm;
	assign fine_switch_S_not = ~fine_switch_S;
	assign fine_switch_drain_not = ~fine_switch_drain;


	reg [8:0] coarse_sca1_top_wait;
	reg [8:0] coarse_sca2_top_wait;
	reg [12:0] fine_sca1_top_wait;
	reg [12:0] fine_sca2_top_wait;

	reg [4:0] state;
	reg [3:0] coarse_b_c;
	reg [3:0] coarse_b_f;
	reg [1:0] coarse_bndset;
	reg [1:0] coarse_drain;
	reg coarse_swtop;
	reg [3:0] fine_b_c;
	reg [3:0] fine_b_f;
	reg [1:0] fine_bndset;
	reg [1:0] fine_drain;
	reg fine_swtop;

	reg [1:0] detskip;

	reg coarse_f_up; // 1 if SCA2 has upper bound voltage
	reg fine_f_up;
	always @(posedge clk) begin //state transitions
		if (rst) 
			state <= S_wait;
		else
			case(state)
				S_wait:
					if(cnvst)
						state <= S_coarse_drain;
					else 
						state <= S_wait;
				S_coarse_drain:
					if(coarse_drain)
						state <= S_coarse_drain;
					else
						state <= S_coarse_comprst;
				S_coarse_comprst:
					if(coarse_b_c)
						state <= S_coarse_c;
					else if(coarse_bndset)
						state <= S_coarse_bndset;
					else
						state <= S_coarse_f;
				S_coarse_c:
					if(coarse_b_c==0)
						state <= S_coarse_bndset;
					else
						state <= S_coarse_comprst;
				S_coarse_bndset:
					if(coarse_bndset)
						state <= S_coarse_bndset;
					else
						state <= S_coarse_swtop;
				S_coarse_swtop:
					if(coarse_swtop)
						state <= S_coarse_swtop;
					else
						state <= S_coarse_comprst;	
				S_coarse_f:
					if(coarse_b_f<=1)
						state <= S_detskip;
					else
						state <= S_coarse_comprst;
				S_detskip:
					if(detskip)
						state <= S_detskip;
					else
						state <= S_fine_f;
				S_fine_comprst:
					state <= S_fine_f;
				S_fine_f:
					if(fine_b_f == 0)
						state <= S_wait;
					else
						state <= S_fine_comprst;

			endcase
	end


	always @(posedge clk) begin //eoc
		if (rst) 
			// reset
			eoc <= 0;
		else 
			if (fine_b_f == 0 && state == S_fine_f) 
				eoc <= 1;
			else
				eoc <= 0;
	end

	always @(posedge clk) begin //coarse_bndset
		if (rst)
			// reset
			coarse_bndset <= 2;
		else 
			case(state)
				S_wait:
					coarse_bndset <= 2;
				S_coarse_bndset:
					if(coarse_bndset)
						coarse_bndset <= coarse_bndset - 1;
			endcase
	end

	always @(posedge clk) begin //coarse_b_c
		if (rst)
			// reset
			coarse_b_c <= 0;
		else 
			case(state)
				S_wait:
					coarse_b_c <= 4'd3;
				S_coarse_c:
					if(coarse_b_c)
						coarse_b_c <= coarse_b_c - 1;
			endcase
	end

	always @(posedge clk) begin //coarse_b_f
		if (rst)
			// reset
			coarse_b_f <= 0;
		else 
			case(state)
				S_wait:
					coarse_b_f <= 4'd3;
				S_coarse_f:
					if(coarse_b_f)
						coarse_b_f <= coarse_b_f - 1;
			endcase
	end

	always @(posedge clk) begin //fine_b_f
		if (rst)
			// reset
			fine_b_f <= 0;
		else 
			case(state)
				S_wait:
					fine_b_f <= 4'd2;
				S_fine_f:
					if(fine_b_f)
						fine_b_f <= fine_b_f - 1;
			endcase
	end

	always @(*) begin //s_clk
		if (rst) 
			// reset
			s_clk <= 1;
		else 
			if (state == S_wait) 
				s_clk <= 1;
			else
				s_clk <= 0;
	end

	always @(posedge clk) begin //coarse_cmp_clk
		if (rst) 
			// reset
			coarse_cmp_clk <= 0;
		else 
			if (state == S_coarse_comprst) 
				coarse_cmp_clk <= 1;
			else
				coarse_cmp_clk <= 0;
	end

	always @(posedge clk) begin //fine_cmp_clk
		if (rst) 
			// reset
			fine_cmp_clk <= 0;
		else 
			if (state == S_fine_comprst) 
				fine_cmp_clk <= 1;
			else
				fine_cmp_clk <= 0;
	end

	always @(posedge clk) begin //coarse_f_up
		if (rst) 
			// reset
			coarse_f_up <= 0;
		else 
			if (state == S_coarse_bndset == 1 && coarse_bndset == 1 && coarse_cmp_out) 
				coarse_f_up <= 1;
	end

	always @(posedge clk) begin //coarse_drain
		if (rst) 
			// reset
			coarse_drain <= 1;
		else 
			if (state == S_coarse_drain && coarse_drain)
				coarse_drain <= coarse_drain - 1;
			else if (state == S_wait)
				coarse_drain <= 2;
	end

	always @(posedge clk) begin //detskip
		if (rst) 
			// reset
			detskip <= 2'd3;
		else 
			if (state == S_detskip)
				detskip <= detskip - 1;
			else if (state == S_wait)
				detskip <= 2'd3;
	end

	always @(posedge clk) begin //coarse_swtop
		if (rst) 
			// reset
			coarse_swtop <= 1;
		else 
			if (state == S_coarse_swtop) 
				coarse_swtop <= 0;
			else if (state == S_wait)
				coarse_swtop <= 1;
	end

	always @(posedge clk) begin //sar
		if (rst) begin
			// reset
			sar <= 0;
		end
		else
			case(state)
				S_wait:
					sar <= 10'b1000000000;
				S_coarse_c: begin
					if(coarse_cmp_out == 0)
						sar[coarse_b_c+4'd6] <= 0;
					if(coarse_b_c)
						sar[coarse_b_c+4'd5] <= 1;
				end
				S_coarse_bndset: begin
					if(coarse_cmp_out == 0)
						sar[4'd6] <= 0;
					sar[4'd5] <= 1;
				end
				S_coarse_f: begin
					if(coarse_cmp_out == 0)
						sar[coarse_b_f+4'd2] <= 0;
					if(coarse_b_f)
						sar[coarse_b_f+1] <= 1;
				end
				S_fine_f: begin
					if(fine_cmp_out == 0)
						sar[fine_b_f] <= 0;
					if(fine_b_f)
						sar[fine_b_f-1] <= 1;
				end
			endcase
	end


	always @(posedge clk) begin //DAC_switch_control
		if (rst) begin
			// reset
			coarse_sca1_top <= 9'b111111111;
			coarse_sca1_btm <= 9'b000000000;
			coarse_sca2_top <= 9'b111111111;
			coarse_sca2_btm <= 9'b000000000;
			coarse_switch_S <= 1;
			coarse_switch_drain <= 0;
		end
		else
			case(state)
				S_wait: begin
					coarse_sca1_top <= 9'b111111111;
					coarse_sca1_btm <= 9'b000000000;
					coarse_sca2_top <= 9'b111111111;
					coarse_sca2_btm <= 9'b000000000;
					coarse_switch_S <= 1;
					coarse_sca1_top_wait <= 9'b000000000;
					coarse_sca2_top_wait <= 9'b000000000;
					coarse_switch_drain <= 0;

					fine_sca1_btm <= 13'd0;
					fine_sca2_btm <= 13'd0;
					fine_switch_S <= 1;
					fine_switch_drain <= 1;
					fine_sca1_top <= 13'b1111111111111;
					fine_sca2_top <= 13'b1111111111111;
					fine_sca1_top_wait <= 13'd0;
					fine_sca2_top_wait <= 13'd0;
				end
				S_coarse_drain:
					case(coarse_drain)
						2'd2:
							coarse_switch_drain <= 1;
						2'd1:
							coarse_switch_drain <= 0;
						2'd0: begin
							coarse_switch_drain <= 0;
							coarse_sca1_btm <= 9'b111100000;
							coarse_sca2_btm <= 9'b111100000;
							end
						endcase
				S_coarse_c:
					case(coarse_b_c)
						4'd3:
							if(coarse_cmp_out) begin
								coarse_sca1_btm[4:3] <= 2'b11;
								coarse_sca2_btm[4:3] <= 2'b11;
							end		

							else begin
								coarse_sca1_btm[8] <= 0;
								coarse_sca2_btm[8] <= 0;
							end
						4'd2:
							if(coarse_cmp_out) begin
								coarse_sca1_btm[2] <= 1;
								coarse_sca2_btm[2] <= 1;
							end		
											
							else begin
								coarse_sca1_btm[7] <= 0;
								coarse_sca2_btm[7] <= 0;
							end
						4'd1:
							if(coarse_cmp_out) begin
								coarse_sca1_btm[1] <= 1;
								coarse_sca2_btm[1] <= 1;
							end		
											
							else begin
								coarse_sca1_btm[6] <= 0;
								coarse_sca2_btm[6] <= 0;
							end

					endcase

				S_coarse_bndset:
					case(coarse_bndset)
						2:
							coarse_switch_S <= 0;
						1:
							if(coarse_cmp_out) begin
								coarse_sca2_btm[0] <= 1;
							end		
											
							else begin
								coarse_sca2_btm[5] <= 0;
							end
						0: begin
							coarse_sca1_top_wait <= 9'b000000010;
							coarse_sca2_top_wait <= 9'b000000010;
							coarse_sca1_top <= 9'b000000000;
							coarse_sca2_top <= 9'b000000000;
						end
							

					endcase

				S_coarse_swtop: 
					if(coarse_swtop)
						coarse_switch_S <= 1;
					else begin
						coarse_sca2_top <= 9'b000000010;
						coarse_sca1_top <= 9'b000000010;
					end

				S_coarse_f:
					case(coarse_b_f)
						4'd3:
							if( (coarse_cmp_out && coarse_f_up == 0) || (coarse_cmp_out == 0 && coarse_f_up) ) begin
								coarse_sca1_top_wait[3:2] <= 2'b11;
								coarse_sca1_top_wait[8] <= 1;
								coarse_sca1_top[2] <= 1;
							end		
											
							else begin
								coarse_sca2_top_wait[3:2] <= 2'b11;
								coarse_sca2_top_wait[8] <= 1;
								coarse_sca2_top[2] <= 1;
							end
						4'd2:
							if( (coarse_cmp_out && coarse_f_up == 0) || (coarse_cmp_out == 0 && coarse_f_up) ) begin
								coarse_sca1_top_wait[7] <= 1;
								coarse_sca1_top_wait[4] <= 1;
								coarse_sca1_top[3] <= coarse_sca1_top_wait[3];
								coarse_sca2_top[3] <= coarse_sca2_top_wait[3];
								coarse_sca1_top[4] <= 1;
							end		
											
							else begin
								coarse_sca2_top_wait[7] <= 1;
								coarse_sca2_top_wait[4] <= 1;
								coarse_sca2_top[3] <= coarse_sca2_top_wait[3];
								coarse_sca1_top[3] <= coarse_sca1_top_wait[3];
								coarse_sca2_top[4] <= 1;							
							end
						4'd1: begin
							if( (coarse_cmp_out && coarse_f_up == 0) || (coarse_cmp_out == 0 && coarse_f_up) ) begin
								coarse_sca1_top_wait[6:5] <= 2'b11;
								coarse_sca1_top[8:7] <= coarse_sca1_top_wait[8:7];
								coarse_sca2_top[8:7] <= coarse_sca2_top_wait[8:7];
								coarse_sca1_top[6:5] <= 2'b11;
							end		
											
							else begin
								coarse_sca2_top_wait[6:5] <= 2'b11;
								coarse_sca2_top[8:7] <= coarse_sca2_top_wait[8:7];
								coarse_sca1_top[8:7] <= coarse_sca1_top_wait[8:7];
								coarse_sca2_top[6:5] <= 2'b11;
							end
							fine_switch_drain <= 0;
							fine_switch_S <= 0;
						end
						// 4'd0:
						// 	if( (coarse_cmp_out && coarse_f_up == 0) || (coarse_cmp_out == 0 && coarse_f_up) ) begin
						// 		coarse_sca1_top[6:5] <= 2'b11;
						// 		coarse_sca1_top[0] <= 1;
						// 	end		
											
						// 	else begin
						// 		coarse_sca2_top[6:5] <= 2'b11;
						// 		coarse_sca2_top[0] <= 1;
						// 	end

					endcase		

				S_detskip: 
					case(detskip)
						3: begin
							fine_sca1_btm[8] <= 1;
							if(sar[9] == 1) begin
								fine_sca1_btm[12] <= 1;
								fine_sca1_btm[7:5] <= 3'b111;
								fine_sca2_btm[12] <= 1;
								fine_sca2_btm[7:5] <= 3'b111;
							end
							if(sar[8] == 1) begin
								fine_sca1_btm[11] <= 1;
								fine_sca1_btm[4:3] <= 2'b11;
								fine_sca2_btm[11] <= 1;
								fine_sca2_btm[4:3] <= 2'b11;
							end
							if(sar[7] == 1) begin
								fine_sca1_btm[10] <= 1;
								fine_sca1_btm[2] <= 1;
								fine_sca2_btm[10] <= 1;
								fine_sca2_btm[2] <= 1;
							end
							if(sar[6] == 1) begin
								fine_sca1_btm[9] <= 1;
								fine_sca1_btm[1] <= 1;
								fine_sca2_btm[9] <= 1;
								fine_sca2_btm[1] <= 1;
							end
							if(sar[5] == 1) begin
								fine_sca2_btm[0] <= 1;
							end
						end
						2: begin //bndset
							fine_sca1_top <= 13'd0;
							fine_sca2_top <= 13'd0;
						end
						1:
							fine_switch_S <= 1;
						0: begin
							if( (sar[4] && fine_f_up == 0) || (sar[4] == 0 && fine_f_up) ) begin
								fine_sca1_top_wait[2] <= 1;
								fine_sca1_top_wait[4] <= 1;
								fine_sca1_top_wait[7] <= 1;
								fine_sca1_top_wait[12] <= 1;
								fine_sca1_top[4] <= 1;
								fine_sca2_top[4] <= 1;
								fine_sca1_top[2] <= 1;
							end
							else begin
								fine_sca2_top_wait[2] <= 1;
								fine_sca2_top_wait[4] <= 1;
								fine_sca2_top_wait[7] <= 1;
								fine_sca2_top_wait[12] <= 1;
								fine_sca1_top[4] <= 1;
								fine_sca2_top[4] <= 1;
								fine_sca2_top[2] <= 1;
							end
							if((sar[3] && fine_f_up == 0) || (sar[3] == 0 && fine_f_up)) begin
								fine_sca1_top_wait[3] <= 1;
								fine_sca1_top_wait[6] <= 1;
								fine_sca1_top_wait[11] <= 1;
								fine_sca1_top[3] <= 1;
							end
							else begin
								fine_sca2_top_wait[3] <= 1;
								fine_sca2_top_wait[6] <= 1;
								fine_sca2_top_wait[11] <= 1;
								fine_sca2_top[3] <= 1;		
							end
						end
					endcase

				
				S_fine_f:
					case(fine_b_f)
					4'd2:
						if( (fine_cmp_out && fine_f_up == 0) || (fine_cmp_out == 0 && fine_f_up) ) begin
							fine_sca1_top_wait[5] <= 1;
							fine_sca1_top_wait[10] <= 1;
							fine_sca1_top[7:6] <= fine_sca1_top_wait[7:6];
							fine_sca2_top[7:6] <= fine_sca2_top_wait[7:6];
							fine_sca1_top[5] <= 1;
						end		
										
						else begin
							fine_sca2_top_wait[5] <= 1;
							fine_sca2_top_wait[10] <= 1;
							fine_sca1_top[7:6] <= fine_sca1_top_wait[7:6];
							fine_sca2_top[7:6] <= fine_sca2_top_wait[7:6];
							fine_sca2_top[5] <= 1;
						end
					4'd1:
						if( (fine_cmp_out && fine_f_up == 0) || (fine_cmp_out == 0 && fine_f_up) ) begin
							fine_sca1_top_wait[9:8] <= 2'b11;
							fine_sca1_top[12:10] <= fine_sca1_top_wait[12:10];
							fine_sca2_top[12:10] <= fine_sca2_top_wait[12:10];
							fine_sca1_top[9:8] <= 2'b11;
						end		
										
						else begin
							fine_sca2_top_wait[9:8] <= 2'b11;
							fine_sca1_top[12:10] <= fine_sca1_top_wait[12:10];
							fine_sca2_top[12:10] <= fine_sca2_top_wait[12:10];
							fine_sca2_top[9:8] <= 2'b11;
							end
					endcase
			endcase
		
	end

endmodule

sar_logic_TSCS_10bit_k7_tb.v
`timescale 1ns/100ps

module sar_logic_TSCS_10bit_k7_tb;
	reg clk;
	reg rst;
	reg cnvst;
	reg coarse_cmp_out;
	reg fine_cmp_out;
	wire [9:0] sar; // digital wire
	wire eoc; // end of conversion
	wire coarse_cmp_clk; // comparator clock
	wire fine_cmp_clk;

	wire s_clk; // bootstrap switch clock

	wire [8:0] coarse_sca1_top;
	wire [8:0] coarse_sca1_btm;
	wire [8:0] coarse_sca2_top;
	wire [8:0] coarse_sca2_btm;
	wire coarse_switch_S;
	wire coarse_switch_drain;

	wire [12:0] fine_sca1_top;
	wire [12:0] fine_sca1_btm;
	wire [12:0] fine_sca2_top;
	wire [12:0] fine_sca2_btm;
	wire fine_switch_S;
	wire fine_switch_drain;

	//INVERTED OUTPUTS
	wire s_clk_not;
	wire [8:0] coarse_sca1_top_not;
	wire [8:0] coarse_sca1_btm_not;
	wire [8:0] coarse_sca2_top_not;
	wire [8:0] coarse_sca2_btm_not;
	wire coarse_switch_S_not;
	wire coarse_switch_drain_not;

	wire [12:0] fine_sca1_top_not;
	wire [12:0] fine_sca1_btm_not;
	wire [12:0] fine_sca2_top_not;
	wire [12:0] fine_sca2_btm_not;
	wire fine_switch_S_not;
	wire fine_switch_drain_not;

	sar_logic_TSCS_10bit_k7 test(	
		clk,
		rst,
		cnvst,
		coarse_cmp_out,
		fine_cmp_out,
		sar, // digital wire
		eoc, // end of conversion
		coarse_cmp_clk, // comparator clock
		fine_cmp_clk,

		s_clk, // bootstrap switch clock

		coarse_sca1_top,
		coarse_sca1_btm,
		coarse_sca2_top,
		coarse_sca2_btm,
		coarse_switch_S,
		coarse_switch_drain,

		fine_sca1_top,
		fine_sca1_btm,
		fine_sca2_top,
		fine_sca2_btm,
		fine_switch_S,
		fine_switch_drain,

		//INVERTED OUTPUTS
		s_clk_not,
		coarse_sca1_top_not,
		coarse_sca1_btm_not,
		coarse_sca2_top_not,
		coarse_sca2_btm_not,
		coarse_switch_S_not,
		coarse_switch_drain_not,

		fine_sca1_top_not,
		fine_sca1_btm_not,
		fine_sca2_top_not,
		fine_sca2_btm_not,
		fine_switch_S_not,
		fine_switch_drain_not
	);

	always #5 clk = !clk;

	initial begin

		$dumpfile("sar_logic_TSCS_10bit_k7.vcd");
		$dumpvars(0, sar_logic_TSCS_10bit_k7_tb);

		clk = 0;
		rst = 1;
		cnvst = 0;
		coarse_cmp_out = 0;
		fine_cmp_out = 0;

		#30

		rst = 0;
		cnvst = 1;

		#20

		cnvst = 1;

		#400

		

		$finish;

	end
endmodule

sar_logic_TSCS_10bit_k7.vcd
$date
	Sat Mar 24 20:49:59 2018
$end
$version
	Icarus Verilog
$end
$timescale
	100ps
$end
$scope module sar_logic_TSCS_10bit_k7_tb $end
$var wire 10 ! sar [9:0] $end
$var wire 1 " s_clk_not $end
$var wire 1 # s_clk $end
$var wire 1 $ fine_switch_drain_not $end
$var wire 1 % fine_switch_drain $end
$var wire 1 & fine_switch_S_not $end
$var wire 1 ' fine_switch_S $end
$var wire 13 ( fine_sca2_top_not [12:0] $end
$var wire 13 ) fine_sca2_top [12:0] $end
$var wire 13 * fine_sca2_btm_not [12:0] $end
$var wire 13 + fine_sca2_btm [12:0] $end
$var wire 13 , fine_sca1_top_not [12:0] $end
$var wire 13 - fine_sca1_top [12:0] $end
$var wire 13 . fine_sca1_btm_not [12:0] $end
$var wire 13 / fine_sca1_btm [12:0] $end
$var wire 1 0 fine_cmp_clk $end
$var wire 1 1 eoc $end
$var wire 1 2 coarse_switch_drain_not $end
$var wire 1 3 coarse_switch_drain $end
$var wire 1 4 coarse_switch_S_not $end
$var wire 1 5 coarse_switch_S $end
$var wire 9 6 coarse_sca2_top_not [8:0] $end
$var wire 9 7 coarse_sca2_top [8:0] $end
$var wire 9 8 coarse_sca2_btm_not [8:0] $end
$var wire 9 9 coarse_sca2_btm [8:0] $end
$var wire 9 : coarse_sca1_top_not [8:0] $end
$var wire 9 ; coarse_sca1_top [8:0] $end
$var wire 9 < coarse_sca1_btm_not [8:0] $end
$var wire 9 = coarse_sca1_btm [8:0] $end
$var wire 1 > coarse_cmp_clk $end
$var reg 1 ? clk $end
$var reg 1 @ cnvst $end
$var reg 1 A coarse_cmp_out $end
$var reg 1 B fine_cmp_out $end
$var reg 1 C rst $end
$scope module test $end
$var wire 1 ? clk $end
$var wire 1 @ cnvst $end
$var wire 1 A coarse_cmp_out $end
$var wire 9 D coarse_sca1_btm_not [8:0] $end
$var wire 9 E coarse_sca1_top_not [8:0] $end
$var wire 9 F coarse_sca2_btm_not [8:0] $end
$var wire 9 G coarse_sca2_top_not [8:0] $end
$var wire 1 4 coarse_switch_S_not $end
$var wire 1 2 coarse_switch_drain_not $end
$var wire 1 B fine_cmp_out $end
$var wire 13 H fine_sca1_btm_not [12:0] $end
$var wire 13 I fine_sca1_top_not [12:0] $end
$var wire 13 J fine_sca2_btm_not [12:0] $end
$var wire 13 K fine_sca2_top_not [12:0] $end
$var wire 1 & fine_switch_S_not $end
$var wire 1 $ fine_switch_drain_not $end
$var wire 1 C rst $end
$var wire 1 " s_clk_not $end
$var reg 4 L coarse_b_c [3:0] $end
$var reg 4 M coarse_b_f [3:0] $end
$var reg 2 N coarse_bndset [1:0] $end
$var reg 1 > coarse_cmp_clk $end
$var reg 2 O coarse_drain [1:0] $end
$var reg 1 P coarse_f_up $end
$var reg 9 Q coarse_sca1_btm [8:0] $end
$var reg 9 R coarse_sca1_top [8:0] $end
$var reg 9 S coarse_sca1_top_wait [8:0] $end
$var reg 9 T coarse_sca2_btm [8:0] $end
$var reg 9 U coarse_sca2_top [8:0] $end
$var reg 9 V coarse_sca2_top_wait [8:0] $end
$var reg 1 5 coarse_switch_S $end
$var reg 1 3 coarse_switch_drain $end
$var reg 1 W coarse_swtop $end
$var reg 2 X detskip [1:0] $end
$var reg 1 1 eoc $end
$var reg 4 Y fine_b_f [3:0] $end
$var reg 1 0 fine_cmp_clk $end
$var reg 1 Z fine_f_up $end
$var reg 13 [ fine_sca1_btm [12:0] $end
$var reg 13 \ fine_sca1_top [12:0] $end
$var reg 13 ] fine_sca1_top_wait [12:0] $end
$var reg 13 ^ fine_sca2_btm [12:0] $end
$var reg 13 _ fine_sca2_top [12:0] $end
$var reg 13 ` fine_sca2_top_wait [12:0] $end
$var reg 1 ' fine_switch_S $end
$var reg 1 % fine_switch_drain $end
$var reg 1 # s_clk $end
$var reg 10 a sar [9:0] $end
$var reg 5 b state [4:0] $end
$upscope $end
$upscope $end
$enddefinitions $end
#0
$dumpvars
bx b
bx a
bx `
bx _
bx ^
bx ]
bx \
bx [
xZ
bx Y
bx X
xW
bx V
bx U
bx T
bx S
bx R
bx Q
xP
bx O
bx N
bx M
bx L
bx K
bx J
bx I
bx H
bx G
bx F
bx E
bx D
1C
0B
0A
0@
0?
x>
bx =
bx <
bx ;
bx :
bx 9
bx 8
bx 7
bx 6
x5
x4
x3
x2
x1
x0
bx /
bx .
bx -
bx ,
bx +
bx *
bx )
bx (
x'
x&
x%
x$
1#
0"
bx !
$end
#50
12
04
b111111111 8
b111111111 F
b0 6
b0 G
b111111111 <
b111111111 D
b0 :
b0 E
b0 b
01
b10 N
b0 L
b0 M
b0 Y
0>
00
0P
b1 O
b11 X
1W
b0 !
b0 a
03
15
b0 9
b0 T
b111111111 7
b111111111 U
b0 =
b0 Q
b111111111 ;
b111111111 R
1?
#100
0?
#150
1?
#200
0?
#250
1?
#300
0?
1@
0C
#350
1"
0#
b0 (
b0 K
b0 ,
b0 I
0$
0&
b1111111111111 *
b1111111111111 J
b1111111111111 .
b1111111111111 H
b0 `
b0 ]
b1111111111111 )
b1111111111111 _
b1111111111111 -
b1111111111111 \
1%
1'
b0 +
b0 ^
b0 /
b0 [
b0 V
b0 S
b1000000000 !
b1000000000 a
b10 O
b10 Y
b11 M
b11 L
b1 b
1?
#400
0?
#450
02
b1 O
13
1?
#500
0?
#550
12
03
b0 O
1?
#600
0?
#650
b11111 8
b11111 F
b11111 <
b11111 D
b10 b
b111100000 9
b111100000 T
b111100000 =
b111100000 Q
1?
#700
0?
#750
1>
b11 b
1?
#800
0?
#850
b100011111 8
b100011111 F
b100011111 <
b100011111 D
b10 b
b10 L
0>
b100000000 !
b100000000 a
b11100000 9
b11100000 T
b11100000 =
b11100000 Q
1?
#900
0?
#950
1>
b11 b
1?
#1000
0?
#1050
b110011111 8
b110011111 F
b110011111 <
b110011111 D
b10 b
b1 L
0>
b10000000 !
b10000000 a
b1100000 9
b1100000 T
b1100000 =
b1100000 Q
1?
#1100
0?
#1150
1>
b11 b
1?
#1200
0?
#1250
b111011111 8
b111011111 F
b111011111 <
b111011111 D
b10 b
b0 L
0>
b1000000 !
b1000000 a
b100000 9
b100000 T
b100000 =
b100000 Q
1?
#1300
0?
#1350
1>
b100 b
1?
#1400
0?
#1450
14
b1 N
0>
b100000 !
b100000 a
05
1?
#1500
0?
#1550
b111111111 8
b111111111 F
b0 9
b0 T
b0 N
1?
#1600
0?
#1650
b111111111 6
b111111111 G
b111111111 :
b111111111 E
b101 b
b0 7
b0 U
b0 ;
b0 R
b10 V
b10 S
1?
#1700
0?
#1750
04
15
0W
1?
#1800
0?
#1850
b111111101 :
b111111101 E
b111111101 6
b111111101 G
b10 b
b10 ;
b10 R
b10 7
b10 U
1?
#1900
0?
#1950
1>
b110 b
1?
#2000
0?
#2050
b111111001 6
b111111001 G
b10 b
b10 M
0>
b10000 !
b10000 a
b110 7
b110 U
b100001110 V
1?
#2100
0?
#2150
1>
b110 b
1?
#2200
0?
#2250
b111100001 6
b111100001 G
b10 b
b1 M
0>
b1000 !
b1000 a
b11110 7
b11110 U
b110011110 V
1?
#2300
0?
#2350
1>
b110 b
1?
#2400
0?
#2450
1&
1$
b1 6
b1 G
b111 b
b0 M
0>
b100 !
b100 a
0'
0%
b111111110 7
b111111110 U
b111111110 V
1?
#2500
0?
#2550
b1111011111111 .
b1111011111111 H
b100000000 /
b100000000 [
b10 X
1?
#2600
0?
#2650
b1111111111111 (
b1111111111111 K
b1111111111111 ,
b1111111111111 I
b1 X
b0 )
b0 _
b0 -
b0 \
1?
#2700
0?
#2750
0&
1'
b0 X
1?
#2800
0?
#2850
b1111111100011 (
b1111111100011 K
b1111111101111 ,
b1111111101111 I
b1011 b
b11 X
b11100 )
b11100 _
b10000 -
b10000 \
b1100011011100 `
1?
#2900
0?
#2950
b1111100000011 (
b1111100000011 K
b11111100 )
b11111100 _
b1110011111100 `
b10 !
b10 a
b1 Y
b1000 b
1?
#3000
0?
#3050
b1011 b
10
1?
#3100
0?
#3150
b11 (
b11 K
b1111111111100 )
b1111111111100 _
b1111111111100 `
b1 !
b1 a
00
b0 Y
b1000 b
1?
#3200
0?
#3250
b1011 b
10
1?
#3300
0?
#3350
0"
1#
b0 !
b0 a
00
11
b0 b
1?
#3400
0?
#3450
1"
0#
b0 (
b0 K
b0 ,
b0 I
0$
b1111111111111 .
b1111111111111 H
b0 6
b0 G
b111111111 <
b111111111 D
b0 :
b0 E
b1 b
01
b10 N
b11 L
b11 M
b10 Y
b10 O
1W
b1000000000 !
b1000000000 a
b0 `
b1111111111111 )
b1111111111111 _
b1111111111111 -
b1111111111111 \
1%
b0 /
b0 [
b0 V
b0 S
b111111111 7
b111111111 U
b0 =
b0 Q
b111111111 ;
b111111111 R
1?
#3500
0?
#3550
02
13
b1 O
1?
#3600
0?
#3650
12
b0 O
03
1?
#3700
0?
#3750
b11111 8
b11111 F
b11111 <
b11111 D
b111100000 9
b111100000 T
b111100000 =
b111100000 Q
b10 b
1?
#3800
0?
#3850
b11 b
1>
1?
#3900
0?
#3950
b100011111 8
b100011111 F
b100011111 <
b100011111 D
b11100000 9
b11100000 T
b11100000 =
b11100000 Q
b100000000 !
b100000000 a
0>
b10 L
b10 b
1?
#4000
0?
#4050
b11 b
1>
1?
#4100
0?
#4150
b110011111 8
b110011111 F
b110011111 <
b110011111 D
b1100000 9
b1100000 T
b1100000 =
b1100000 Q
b10000000 !
b10000000 a
0>
b1 L
b10 b
1?
#4200
0?
#4250
b11 b
1>
1?
#4300
0?
#4350
b111011111 8
b111011111 F
b111011111 <
b111011111 D
b100000 9
b100000 T
b100000 =
b100000 Q
b1000000 !
b1000000 a
0>
b0 L
b10 b
1?
#4400
0?
#4450
b100 b
1>
1?
