sar_logic_CS_10bit_k5.v
module sar_logic_CS_10bit_k5(
	input clk,
	input rst,
	input cnvst,
	input cmp_out,
	input cmp_out_coarse,
	output reg [9:0] sar, // digital output
	output reg eoc, // end of conversion
	output reg cmp_clk, // comparator clock
	output reg cmp_clk_coarse,

	output reg s_clk, // bootstrap switch clock
	output reg [19:0] fine_btm,
	output reg [9:0] coarse_btm,
	output reg fine_switch_drain,
	output reg coarse_switch_drain,

	//INVERTED OUTPUTS
	output s_clk_not,
	output [19:0] fine_btm_not,
	output [9:0] coarse_btm_not,
	output fine_switch_drain_not,
	output coarse_switch_drain_not
	);
	
	// 256 128 64 32 16 8  4  2  1  1  256 128 64 32 16 8 4 2 1 1
	//  19  18 17 16 15 14 13 12 11 10   9   8  7  6  5 4 3 2 1 0 
	parameter S_wait						= 4'd0;
	parameter S_drain 					= 4'd1;
	parameter S_comprst					= 4'd2;
	parameter S_ds							= 4'd3;
	parameter S_comprst_coarse 	= 4'd4;
	parameter S_decide					= 4'd5;

	assign s_clk_not = ~s_clk;
	assign fine_btm_not = ~fine_btm;
	assign fine_switch_drain_not = ~fine_switch_drain;
	assign coarse_btm_not = ~coarse_btm;
	assign coarse_switch_drain_not = ~coarse_switch_drain;

	reg [3:0] state;
	reg drain;
	reg [3:0] b;
	reg [2:0] b_coarse;
	reg ds;

	reg fine_up; // 1 if SCA2 has upper bound voltage

	always @(posedge clk) begin //state transitions
		if (rst) 
			state <= S_wait;
		else
			case(state)
				S_wait:
					if(cnvst)
						state <= S_drain;
					else 
						state <= S_wait;
				S_drain:
					if(drain)
						state <= S_drain;
					else
						state <= S_comprst_coarse;
				S_comprst:
					state <= S_decide;
				S_comprst_coarse:
					state <= S_decide;
				S_ds:
					if(ds==0)
						state <= S_comprst;
				S_decide:
					if(b==0)
						state <= S_wait;
					else
						if(b_coarse)
							state <= S_comprst_coarse;
						else if(ds)
							state <= S_ds;
						else 
							state <= S_comprst;

			endcase
	end


	always @(posedge clk) begin //eoc
		if (rst) 
			// reset
			eoc <= 0;
		else 
			if (b == 0 && state == S_decide) 
				eoc <= 1;
			else
				eoc <= 0;
	end


	always @(posedge clk) begin //b
		if (rst)
			// reset
			b <= 0;
		else 
			case(state)
				S_wait:
					b <= 4'd9;
				S_decide:
					if(b)
						b <= b - 1;
			endcase
	end

	always @(posedge clk) begin //b_coarse
		if (rst)
			// reset
			b_coarse <= 3'd4;
		else 
			case(state)
				S_wait:
					b_coarse <= 3'd4;
				S_decide:
					if(b_coarse)
						b_coarse <= b_coarse - 1;
			endcase
	end

	always @(*) begin //s_clk
		if (rst) 
			// reset
			s_clk <= 1;
		else 
			if (state == S_wait) 
				s_clk <= 1;
			else
				s_clk <= 0;
	end

	always @(posedge clk) begin //cmp_clk
		if (rst) 
			// reset
			cmp_clk <= 0;
		else 
			if (state == S_comprst) 
				cmp_clk <= 1;
			else
				cmp_clk <= 0;
	end

	always @(posedge clk) begin //cmp_clk_coarse
		if (rst) 
			// reset
			cmp_clk_coarse <= 0;
		else 
			if (state == S_comprst_coarse) 
				cmp_clk_coarse <= 1;
			else
				cmp_clk_coarse <= 0;
	end

	always @(posedge clk) begin //drain
		if (rst) 
			// reset
			drain <= 1;
		else 
			if (state == S_drain)
				drain <= 0;
			else if (state == S_wait)
				drain <= 1;
	end

	always @(posedge clk) begin //ds
		if (rst) 
			// reset
			ds <= 1;
		else 
			if (state == S_ds)
				ds <= 0;
			else if (state == S_wait)
				ds <= 1;
	end

	always @(posedge clk) begin //sar
		if (rst) begin
			// reset
			sar <= 0;
		end
		else
			case(state)
				S_wait:
					sar <= 10'b1000000000;
				S_decide: begin
					if(cmp_clk_coarse) begin
						if(cmp_out_coarse == 0)
							sar[b] <= 0;
						if(b)
						 sar[b-1] <= 1;
					end
					else begin
						if(cmp_out == 0)
							sar[b] <= 0;
						if(b)
							sar[b-1] <= 1;
					end
				end
				
			endcase
	end


	always @(posedge clk) begin //DAC_switch_control
		if (rst) begin
			// reset
			fine_btm <= 20'd0;
			fine_switch_drain <= 1;
			coarse_switch_drain <= 1;
			coarse_btm <= 10'd0;
		end
		else
			case(state)
				S_wait: begin
					fine_btm <= 20'd0;
					coarse_btm <= 10'd0;
					fine_switch_drain <= 1;
					coarse_switch_drain <= 1;
				end
				S_drain:
					case(drain)
						1:
							coarse_switch_drain <= 0;
						0: begin
							coarse_btm <= 10'b1111100000;
							end
						endcase
				S_ds:
					case(ds)
						1:
							fine_switch_drain <= 0;
						0: begin
							if(sar[9] == 1) begin
								fine_btm[19] <= 1;
								fine_btm[9] <= 1;
							end
							if(sar[8] == 1) begin
								fine_btm[18] <= 1;
								fine_btm[8] <= 1;
							end
							if(sar[7] == 1) begin
								fine_btm[17] <= 1;
								fine_btm[7] <= 1;
							end
							if(sar[6] == 1) begin
								fine_btm[16] <= 1;
								fine_btm[6] <= 1;
							end
							if(sar[5] == 1) begin
								fine_btm[15] <= 1;
								fine_btm[5] <= 1;
							end
							fine_btm[14:10] <= 5'b11111;
						end

					endcase
				S_decide:
					if(cmp_clk_coarse) 
						if(cmp_out_coarse) begin
							coarse_btm[b_coarse] <= 1;
						end		

						else begin
							coarse_btm[b_coarse+5] <= 0;
						end

					else
						if(cmp_out) begin
							fine_btm[b] <= 1;
						end		

						else begin
							fine_btm[b+10] <= 0;
						end

			endcase
		
	end

endmodule

sar_logic_CS_10bit_k5_tb.v
`timescale 1ns/100ps

module sar_logic_CS_10bit_k5_tb;
	reg clk;
	reg rst;
	reg cnvst;
	reg cmp_out;
	reg cmp_out_coarse;
	wire [9:0] sar; // digital output
	wire eoc; // end of conversion
	wire cmp_clk; // comparator clock
	wire cmp_clk_coarse;

	wire s_clk; // bootstrap switch clock
	wire [19:0] fine_btm;
	wire [9:0] coarse_btm;
	wire fine_switch_drain;
	wire coarse_switch_drain;

	//INVERTED OUTPUTS
	wire s_clk_not;
	wire [19:0] fine_btm_not;
	wire [9:0] coarse_btm_not;
	wire fine_switch_drain_not;
	wire coarse_switch_drain_not;


	sar_logic_CS_10bit_k5 test(clk, rst, cnvst, cmp_out, cmp_out_coarse, sar, eoc, cmp_clk, cmp_clk_coarse, s_clk, fine_btm, coarse_btm, fine_switch_drain, coarse_switch_drain, s_clk_not, fine_btm_not, coarse_btm_not, fine_switch_drain_not, coarse_switch_drain_not);

	always #5 clk = !clk;

	initial begin

		$dumpfile("sar_logic_CS_10bit_k5.vcd");
		$dumpvars(0, sar_logic_CS_10bit_k5_tb);

		clk = 0;
		rst = 1;
		cnvst = 0;
		cmp_out = 1;
		cmp_out_coarse = 1;

		#30

		rst = 0;
		cmp_out = 0;
		cnvst = 1;

		#20

		cnvst = 1;

		#300

		

		$finish;

	end
endmodule

sar_logic_CS_10bit_k5.vcd
$date
	Mon Mar 12 02:46:19 2018
$end
$version
	Icarus Verilog
$end
$timescale
	100ps
$end
$scope module sar_logic_CS_10bit_k5_tb $end
$var wire 10 ! sar [9:0] $end
$var wire 1 " s_clk_not $end
$var wire 1 # s_clk $end
$var wire 1 $ fine_switch_drain_not $end
$var wire 1 % fine_switch_drain $end
$var wire 20 & fine_btm_not [19:0] $end
$var wire 20 ' fine_btm [19:0] $end
$var wire 1 ( eoc $end
$var wire 1 ) coarse_switch_drain_not $end
$var wire 1 * coarse_switch_drain $end
$var wire 10 + coarse_btm_not [9:0] $end
$var wire 10 , coarse_btm [9:0] $end
$var wire 1 - cmp_clk_coarse $end
$var wire 1 . cmp_clk $end
$var reg 1 / clk $end
$var reg 1 0 cmp_out $end
$var reg 1 1 cmp_out_coarse $end
$var reg 1 2 cnvst $end
$var reg 1 3 rst $end
$scope module test $end
$var wire 1 / clk $end
$var wire 1 0 cmp_out $end
$var wire 1 1 cmp_out_coarse $end
$var wire 1 2 cnvst $end
$var wire 10 4 coarse_btm_not [9:0] $end
$var wire 1 ) coarse_switch_drain_not $end
$var wire 20 5 fine_btm_not [19:0] $end
$var wire 1 $ fine_switch_drain_not $end
$var wire 1 3 rst $end
$var wire 1 " s_clk_not $end
$var reg 4 6 b [3:0] $end
$var reg 3 7 b_coarse [2:0] $end
$var reg 1 . cmp_clk $end
$var reg 1 - cmp_clk_coarse $end
$var reg 10 8 coarse_btm [9:0] $end
$var reg 1 * coarse_switch_drain $end
$var reg 1 9 drain $end
$var reg 1 : ds $end
$var reg 1 ( eoc $end
$var reg 20 ; fine_btm [19:0] $end
$var reg 1 % fine_switch_drain $end
$var reg 1 # s_clk $end
$var reg 10 < sar [9:0] $end
$var reg 4 = state [3:0] $end
$upscope $end
$upscope $end
$enddefinitions $end
#0
$dumpvars
bx =
bx <
bx ;
x:
x9
bx 8
bx 7
bx 6
bx 5
bx 4
13
02
11
10
0/
x.
x-
bx ,
bx +
x*
x)
x(
bx '
bx &
x%
x$
1#
0"
bx !
$end
#50
b1111111111 +
b1111111111 4
0)
0$
b11111111111111111111 &
b11111111111111111111 5
b0 =
0(
b0 6
b100 7
0.
0-
19
1:
b0 !
b0 <
b0 ,
b0 8
1*
1%
b0 '
b0 ;
1/
#100
0/
#150
1/
#200
0/
#250
1/
#300
0/
12
00
03
#350
1"
0#
b1000000000 !
b1000000000 <
b1001 6
b1 =
1/
#400
0/
#450
1)
09
0*
1/
#500
0/
#550
b11111 +
b11111 4
b1111100000 ,
b1111100000 8
b100 =
1/
#600
0/
#650
b101 =
1-
1/
#700
0/
#750
b1111 +
b1111 4
b1111110000 ,
b1111110000 8
b1100000000 !
b1100000000 <
0-
b11 7
b1000 6
b100 =
1/
#800
0/
#850
b101 =
1-
1/
#900
0/
#950
b111 +
b111 4
b1111111000 ,
b1111111000 8
b1110000000 !
b1110000000 <
0-
b10 7
b111 6
b100 =
1/
#1000
0/
#1050
b101 =
1-
1/
#1100
0/
#1150
b11 +
b11 4
b1111111100 ,
b1111111100 8
b1111000000 !
b1111000000 <
0-
b1 7
b110 6
b100 =
1/
#1200
0/
#1250
b101 =
1-
1/
#1300
0/
#1350
b1 +
b1 4
b1111111110 ,
b1111111110 8
b1111100000 !
b1111100000 <
0-
b0 7
b101 6
b100 =
1/
#1400
0/
#1450
b101 =
1-
1/
#1500
0/
#1550
b0 +
b0 4
b1111111111 ,
b1111111111 8
b1111110000 !
b1111110000 <
0-
b100 6
b11 =
1/
#1600
0/
#1650
1$
0:
0%
1/
#1700
0/
#1750
b11111 &
b11111 5
b11111111111111100000 '
b11111111111111100000 ;
b10 =
1/
#1800
0/
#1850
b101 =
1.
1/
#1900
0/
#1950
b100000000011111 &
b100000000011111 5
b11111011111111100000 '
b11111011111111100000 ;
b1111101000 !
b1111101000 <
0.
b11 6
b10 =
1/
#2000
0/
#2050
b101 =
1.
1/
#2100
0/
#2150
b110000000011111 &
b110000000011111 5
b11111001111111100000 '
b11111001111111100000 ;
b1111100100 !
b1111100100 <
0.
b10 6
b10 =
1/
#2200
0/
#2250
b101 =
1.
1/
#2300
0/
#2350
b111000000011111 &
b111000000011111 5
b11111000111111100000 '
b11111000111111100000 ;
b1111100010 !
b1111100010 <
0.
b1 6
b10 =
1/
#2400
0/
#2450
b101 =
1.
1/
#2500
0/
#2550
b111100000011111 &
b111100000011111 5
b11111000011111100000 '
b11111000011111100000 ;
b1111100001 !
b1111100001 <
0.
b0 6
b10 =
1/
#2600
0/
#2650
b101 =
1.
1/
#2700
0/
#2750
0"
1#
b111110000011111 &
b111110000011111 5
b11111000001111100000 '
b11111000001111100000 ;
b1111100000 !
b1111100000 <
0.
1(
b0 =
1/
#2800
0/
#2850
1"
0#
0)
0$
b1111111111 +
b1111111111 4
b11111111111111111111 &
b11111111111111111111 5
b1 =
0(
b1001 6
b100 7
19
1:
b1000000000 !
b1000000000 <
1*
1%
b0 ,
b0 8
b0 '
b0 ;
1/
#2900
0/
#2950
1)
0*
09
1/
#3000
0/
#3050
b11111 +
b11111 4
b100 =
b1111100000 ,
b1111100000 8
1/
#3100
0/
#3150
1-
b101 =
1/
#3200
0/
#3250
b1111 +
b1111 4
b100 =
b1000 6
b11 7
0-
b1100000000 !
b1100000000 <
b1111110000 ,
b1111110000 8
1/
#3300
0/
#3350
1-
b101 =
1/
#3400
0/
#3450
b111 +
b111 4
b100 =
b111 6
b10 7
0-
b1110000000 !
b1110000000 <
b1111111000 ,
b1111111000 8
1/
