sar_logic_TSCS_10bit.v
module sar_logic_TSCS_10bit(
	input clk,
	input rst,
	input cnvst,
	input cmp_out,
	output reg [9:0] sar, // digital output
	output reg eoc, // end of conversion
	output reg cmp_clk, // comparator clock

	output reg s_clk, // bootstrap switch clock
	output reg [12:0] fine_sca1_top,
	output reg [12:0] fine_sca1_btm,
	output reg [12:0] fine_sca2_top,
	output reg [12:0] fine_sca2_btm,
	output reg fine_switch_S,
	output reg fine_switch_drain,

	//INVERTED OUTPUTS
	output s_clk_not,
	output [12:0] fine_sca1_top_not,
	output [12:0] fine_sca1_btm_not,
	output [12:0] fine_sca2_top_not,
	output [12:0] fine_sca2_btm_not,
	output fine_switch_S_not,
	output fine_switch_drain_not
	);
	
	parameter S_wait		= 3'd0;
	parameter S_drain 	= 3'd1;
	parameter S_comprst	= 3'd2;
	parameter S_coarse	= 3'd3;
	parameter S_bndset	= 3'd4;
	parameter S_swtop		= 3'd5;
	parameter S_fine		= 3'd6;

	assign s_clk_not = ~s_clk;
	assign fine_sca1_top_not = ~fine_sca1_top;
	assign fine_sca1_btm_not = ~fine_sca1_btm;
	assign fine_sca2_top_not = ~fine_sca2_top;
	assign fine_sca2_btm_not = ~fine_sca2_btm;
	assign fine_switch_S_not = ~fine_switch_S;
	assign fine_switch_drain_not = ~fine_switch_drain;

	reg [12:0] fine_sca1_top_wait;
	reg [12:0] fine_sca2_top_wait;

	reg [3:0] state;
	reg [3:0] b_coarse;
	reg [3:0] b_fine;
	reg [1:0] bndset;
	reg [1:0] drain;
	reg swtop;

	reg fine_up; // 1 if SCA2 has upper bound voltage

	always @(posedge clk) begin //state transitions
		if (rst) 
			state <= S_wait;
		else
			case(state)
				S_wait:
					if(cnvst)
						state <= S_drain;
					else 
						state <= S_wait;
				S_drain:
					if(drain)
						state <= S_drain;
					else
						state <= S_comprst;
				S_comprst:
					if(b_coarse)
						state <= S_coarse;
					else if(bndset)
						state <= S_bndset;
					else
						state <= S_fine;
				S_coarse:
					if(b_coarse==0)
						state <= S_bndset;
					else
						state <= S_comprst;
				S_bndset:
					if(bndset)
						state <= S_bndset;
					else
						state <= S_swtop;
				S_swtop:
					if(swtop)
						state <= S_swtop;
					else
						state <= S_comprst;	
				S_fine:
					if(b_fine==0)
						state <= S_wait;
					else
						state <= S_comprst;

			endcase
	end


	always @(posedge clk) begin //eoc
		if (rst) 
			// reset
			eoc <= 0;
		else 
			if (b_fine == 0 && state == S_fine) 
				eoc <= 1;
			else
				eoc <= 0;
	end

	always @(posedge clk) begin //bndset
		if (rst)
			// reset
			bndset <= 2;
		else 
			case(state)
				S_wait:
					bndset <= 2;
				S_bndset:
					if(bndset)
						bndset <= bndset - 1;
			endcase
	end

	always @(posedge clk) begin //b_coarse
		if (rst)
			// reset
			b_coarse <= 0;
		else 
			case(state)
				S_wait:
					b_coarse <= 4'd4;
				S_coarse:
					if(b_coarse)
						b_coarse <= b_coarse - 1;
			endcase
	end

	always @(posedge clk) begin //b_fine
		if (rst)
			// reset
			b_fine <= 0;
		else 
			case(state)
				S_wait:
					b_fine <= 4'd4;
				S_fine:
					if(b_fine)
						b_fine <= b_fine - 1;
			endcase
	end

	always @(*) begin //s_clk
		if (rst) 
			// reset
			s_clk <= 1;
		else 
			if (state == S_wait) 
				s_clk <= 1;
			else
				s_clk <= 0;
	end

	always @(posedge clk) begin //cmp_clk
		if (rst) 
			// reset
			cmp_clk <= 0;
		else 
			if (state == S_comprst) 
				cmp_clk <= 1;
			else
				cmp_clk <= 0;
	end

	always @(posedge clk) begin //fine_up
		if (rst) 
			// reset
			fine_up <= 0;
		else 
			if (state == S_bndset == 1 && bndset == 1 && cmp_out) 
				fine_up <= 1;
	end

	always @(posedge clk) begin //drain
		if (rst) 
			// reset
			drain <= 1;
		else 
			if (state == S_drain && drain)
				drain <= drain - 1;
			else if (state == S_wait)
				drain <= 2;
	end

	always @(posedge clk) begin //swtop
		if (rst) 
			// reset
			swtop <= 1;
		else 
			if (state == S_swtop) 
				swtop <= 0;
			else if (state == S_wait)
				swtop <= 1;
	end

	always @(posedge clk) begin //sar
		if (rst) begin
			// reset
			sar <= 0;
		end
		else
			case(state)
				S_wait:
					sar <= 10'b1000000000;
				S_coarse: begin
					if(cmp_out == 0)
						sar[b_coarse+4'd5] <= 0;
					if(b_coarse)
						sar[b_coarse+4'd4] <= 1;
				end
				S_bndset: begin
					if(cmp_out == 0)
						sar[4'd5] <= 0;
					sar[4'd4] <= 1;
				end
				S_fine: begin
					if(cmp_out == 0)
						sar[b_fine] <= 0;
					if(b_fine)
						sar[b_fine-1] <= 1;
				end
			endcase
	end


	always @(posedge clk) begin //DAC_switch_control
		if (rst) begin
			// reset
			fine_sca1_top <= 13'b1111111111111;
			fine_sca1_btm <= 13'b0000000000000;
			fine_sca2_top <= 13'b1111111111111;
			fine_sca2_btm <= 13'b0000000000000;
			fine_switch_S <= 1;
			fine_switch_drain <= 0;
		end
		else
			case(state)
				S_wait: begin
					fine_sca1_top <= 13'b1111111111111;
					fine_sca1_btm <= 13'b0000000000000;
					fine_sca2_top <= 13'b1111111111111;
					fine_sca2_btm <= 13'b0000000000000;
					fine_switch_S <= 1;
					fine_sca1_top_wait <= 13'b0000000000000;
					fine_sca2_top_wait <= 13'b0000000000000;
					fine_switch_drain <= 0;
				end
				S_drain:
					case(drain)
						2'd2:
							fine_switch_drain <= 1;
						2'd1:
							fine_switch_drain <= 0;
						2'd0: begin
							fine_switch_drain <= 0;
							fine_sca1_btm <= 13'b1111100000000;
							fine_sca2_btm <= 13'b1111100000000;
							end
						endcase
				S_coarse:
					case(b_coarse)
						4'd4:
							if(cmp_out) begin
								fine_sca1_btm[7:5] <= 3'b111;
								fine_sca2_btm[7:5] <= 3'b111;
							end		

							else begin
								fine_sca1_btm[12] <= 0;
								fine_sca2_btm[12] <= 0;
							end
						4'd3:
							if(cmp_out) begin
								fine_sca1_btm[4:3] <= 2'b11;
								fine_sca2_btm[4:3] <= 2'b11;
							end		

							else begin
								fine_sca1_btm[11] <= 0;
								fine_sca2_btm[11] <= 0;
							end
						4'd2:
							if(cmp_out) begin
								fine_sca1_btm[2] <= 1;
								fine_sca2_btm[2] <= 1;
							end		
											
							else begin
								fine_sca1_btm[10] <= 0;
								fine_sca2_btm[10] <= 0;
							end
						4'd1:
							if(cmp_out) begin
								fine_sca1_btm[1] <= 1;
								fine_sca2_btm[1] <= 1;
							end		
											
							else begin
								fine_sca1_btm[9] <= 0;
								fine_sca2_btm[9] <= 0;
							end

					endcase

				S_bndset:
					case(bndset)
						2:
							fine_switch_S <= 0;
						1:
							if(cmp_out) begin
								fine_sca2_btm[0] <= 1;
							end		
											
							else begin
								fine_sca2_btm[8] <= 0;
							end
						0: begin
							fine_sca1_top_wait <= 13'b0000000000010;
							fine_sca2_top_wait <= 13'b0000000000010;
							fine_sca1_top <= 13'b0000000000000;
							fine_sca2_top <= 13'b0000000000000;
						end
							

					endcase

				S_swtop: 
					if(swtop)
						fine_switch_S <= 1;
					else begin
						fine_sca2_top <= 13'b0000000000010;
						fine_sca1_top <= 13'b0000000000010;
					end

				S_fine:
					case(b_fine)
						4'd4:
							if( (cmp_out && fine_up == 0) || (cmp_out == 0 && fine_up) ) begin
								fine_sca1_top_wait[2] <= 1;
								fine_sca1_top_wait[4] <= 1;
								fine_sca1_top_wait[7] <= 1;
								fine_sca1_top_wait[12] <= 1;
								fine_sca1_top[2] <= 1;
							end		
											
							else begin
								fine_sca2_top_wait[2] <= 1;
								fine_sca2_top_wait[4] <= 1;
								fine_sca2_top_wait[7] <= 1;
								fine_sca2_top_wait[12] <= 1;
								fine_sca2_top[2] <= 1;
							end
						4'd3:
							if( (cmp_out && fine_up == 0) || (cmp_out == 0 && fine_up) ) begin
								fine_sca1_top_wait[3] <= 1;
								fine_sca1_top_wait[6] <= 1;
								fine_sca1_top_wait[11] <= 1;
								fine_sca1_top[4] <= fine_sca1_top_wait[4];
								fine_sca2_top[4] <= fine_sca2_top_wait[4];
								fine_sca1_top[3] <= 1;
							end		
											
							else begin
								fine_sca2_top_wait[3] <= 1;
								fine_sca2_top_wait[6] <= 1;
								fine_sca2_top_wait[11] <= 1;
								fine_sca1_top[4] <= fine_sca1_top_wait[4];
								fine_sca2_top[4] <= fine_sca2_top_wait[4];
								fine_sca2_top[3] <= 1;					
							end
						4'd2:
							if( (cmp_out && fine_up == 0) || (cmp_out == 0 && fine_up) ) begin
								fine_sca1_top_wait[5] <= 1;
								fine_sca1_top_wait[10] <= 1;
								fine_sca1_top[7:6] <= fine_sca1_top_wait[7:6];
								fine_sca2_top[7:6] <= fine_sca2_top_wait[7:6];
								fine_sca1_top[5] <= 1;
							end		
											
							else begin
								fine_sca2_top_wait[5] <= 1;
								fine_sca2_top_wait[10] <= 1;
								fine_sca1_top[7:6] <= fine_sca1_top_wait[7:6];
								fine_sca2_top[7:6] <= fine_sca2_top_wait[7:6];
								fine_sca2_top[5] <= 1;
							end
						4'd1:
							if( (cmp_out && fine_up == 0) || (cmp_out == 0 && fine_up) ) begin
								fine_sca1_top_wait[9:8] <= 2'b11;
								fine_sca1_top[12:10] <= fine_sca1_top_wait[12:10];
								fine_sca2_top[12:10] <= fine_sca2_top_wait[12:10];
								fine_sca1_top[9:8] <= 2'b11;
							end		
											
							else begin
								fine_sca2_top_wait[9:8] <= 2'b11;
								fine_sca1_top[12:10] <= fine_sca1_top_wait[12:10];
								fine_sca2_top[12:10] <= fine_sca2_top_wait[12:10];
								fine_sca2_top[9:8] <= 2'b11;
							end
						// 4'd0:
						// 	if( (cmp_out && fine_up == 0) || (cmp_out == 0 && fine_up) ) begin
						// 		fine_sca1_top[6:5] <= 2'b11;
						// 		fine_sca1_top[0] <= 1;
						// 	end		
											
						// 	else begin
						// 		fine_sca2_top[6:5] <= 2'b11;
						// 		fine_sca2_top[0] <= 1;
						// 	end

					endcase				
			endcase
		
	end

endmodule

sar_logic_TSCS_10bit_tb.v
`timescale 1ns/100ps

module sar_logic_TSCS_10bit_tb;
	reg clk;
	reg rst;
	reg cnvst;
	reg cmp_out;
	wire [9:0] sar;
	wire eoc;
	wire cmp_clk;
	wire s_clk;

	wire [12:0] fine_sca1_top;
	wire [12:0] fine_sca1_btm;
	wire [12:0] fine_sca2_top;
	wire [12:0] fine_sca2_btm;
	wire fine_switch_S;

	wire s_clk_not;
	wire [12:0] fine_sca1_top_not;
	wire [12:0] fine_sca1_btm_not;
	wire [12:0] fine_sca2_top_not;
	wire [12:0] fine_sca2_btm_not;
	wire fine_switch_S_not;


	sar_logic_TSCS_10bit test(clk, rst, cnvst, cmp_out, sar, eoc, cmp_clk, s_clk, fine_sca1_top, fine_sca1_btm, fine_sca2_top, fine_sca2_btm, fine_switch_S, fine_switch_drain, s_clk_not, fine_sca1_top_not,
		fine_sca1_btm_not, fine_sca2_top_not, fine_sca2_btm_not, fine_switch_S_not, fine_switch_drain_not);

	always #5 clk = !clk;

	initial begin

		$dumpfile("sar_logic_TSCS_10bit.vcd");
		$dumpvars(0, sar_logic_TSCS_10bit_tb);

		clk = 0;
		rst = 1;
		cnvst = 0;
		cmp_out = 1;

		#30

		rst = 0;
		cmp_out = 1;
		cnvst = 1;

		#20

		cnvst = 1;

		#300

		

		$finish;

	end
endmodule

sar_logic_TSCS_10bit.vcd
$date
	Wed Mar 14 18:18:22 2018
$end
$version
	Icarus Verilog
$end
$timescale
	100ps
$end
$scope module sar_logic_TSCS_10bit_tb $end
$var wire 10 ! sar [9:0] $end
$var wire 1 " s_clk_not $end
$var wire 1 # s_clk $end
$var wire 1 $ fine_switch_drain_not $end
$var wire 1 % fine_switch_drain $end
$var wire 1 & fine_switch_S_not $end
$var wire 1 ' fine_switch_S $end
$var wire 13 ( fine_sca2_top_not [12:0] $end
$var wire 13 ) fine_sca2_top [12:0] $end
$var wire 13 * fine_sca2_btm_not [12:0] $end
$var wire 13 + fine_sca2_btm [12:0] $end
$var wire 13 , fine_sca1_top_not [12:0] $end
$var wire 13 - fine_sca1_top [12:0] $end
$var wire 13 . fine_sca1_btm_not [12:0] $end
$var wire 13 / fine_sca1_btm [12:0] $end
$var wire 1 0 eoc $end
$var wire 1 1 cmp_clk $end
$var reg 1 2 clk $end
$var reg 1 3 cmp_out $end
$var reg 1 4 cnvst $end
$var reg 1 5 rst $end
$scope module test $end
$var wire 1 2 clk $end
$var wire 1 3 cmp_out $end
$var wire 1 4 cnvst $end
$var wire 13 6 fine_sca1_btm_not [12:0] $end
$var wire 13 7 fine_sca1_top_not [12:0] $end
$var wire 13 8 fine_sca2_btm_not [12:0] $end
$var wire 13 9 fine_sca2_top_not [12:0] $end
$var wire 1 & fine_switch_S_not $end
$var wire 1 $ fine_switch_drain_not $end
$var wire 1 5 rst $end
$var wire 1 " s_clk_not $end
$var reg 4 : b_coarse [3:0] $end
$var reg 4 ; b_fine [3:0] $end
$var reg 2 < bndset [1:0] $end
$var reg 1 1 cmp_clk $end
$var reg 2 = drain [1:0] $end
$var reg 1 0 eoc $end
$var reg 13 > fine_sca1_btm [12:0] $end
$var reg 13 ? fine_sca1_top [12:0] $end
$var reg 13 @ fine_sca1_top_wait [12:0] $end
$var reg 13 A fine_sca2_btm [12:0] $end
$var reg 13 B fine_sca2_top [12:0] $end
$var reg 13 C fine_sca2_top_wait [12:0] $end
$var reg 1 ' fine_switch_S $end
$var reg 1 % fine_switch_drain $end
$var reg 1 D fine_up $end
$var reg 1 # s_clk $end
$var reg 10 E sar [9:0] $end
$var reg 4 F state [3:0] $end
$var reg 1 G swtop $end
$upscope $end
$upscope $end
$enddefinitions $end
#0
$dumpvars
xG
bx F
bx E
xD
bx C
bx B
bx A
bx @
bx ?
bx >
bx =
bx <
bx ;
bx :
bx 9
bx 8
bx 7
bx 6
15
04
13
02
x1
x0
bx /
bx .
bx -
bx ,
bx +
bx *
bx )
bx (
x'
x&
x%
x$
1#
0"
bx !
$end
#50
1$
0&
b1111111111111 *
b1111111111111 8
b0 (
b0 9
b1111111111111 .
b1111111111111 6
b0 ,
b0 7
b0 F
00
b10 <
b0 :
b0 ;
01
0D
b1 =
1G
b0 !
b0 E
0%
1'
b0 +
b0 A
b1111111111111 )
b1111111111111 B
b0 /
b0 >
b1111111111111 -
b1111111111111 ?
12
#100
02
#150
12
#200
02
#250
12
#300
02
14
05
#350
1"
0#
b0 C
b0 @
b1000000000 !
b1000000000 E
b10 =
b100 ;
b100 :
b1 F
12
#400
02
#450
0$
b1 =
1%
12
#500
02
#550
1$
0%
b0 =
12
#600
02
#650
b11111111 *
b11111111 8
b11111111 .
b11111111 6
b10 F
b1111100000000 +
b1111100000000 A
b1111100000000 /
b1111100000000 >
12
#700
02
#750
11
b11 F
12
#800
02
#850
b11111 *
b11111 8
b11111 .
b11111 6
b10 F
b11 :
01
b1100000000 !
b1100000000 E
b1111111100000 +
b1111111100000 A
b1111111100000 /
b1111111100000 >
12
#900
02
#950
11
b11 F
12
#1000
02
#1050
b111 *
b111 8
b111 .
b111 6
b10 F
b10 :
01
b1110000000 !
b1110000000 E
b1111111111000 +
b1111111111000 A
b1111111111000 /
b1111111111000 >
12
#1100
02
#1150
11
b11 F
12
#1200
02
#1250
b11 *
b11 8
b11 .
b11 6
b10 F
b1 :
01
b1111000000 !
b1111000000 E
b1111111111100 +
b1111111111100 A
b1111111111100 /
b1111111111100 >
12
#1300
02
#1350
11
b11 F
12
#1400
02
#1450
b1 *
b1 8
b1 .
b1 6
b10 F
b0 :
01
b1111100000 !
b1111100000 E
b1111111111110 +
b1111111111110 A
b1111111111110 /
b1111111111110 >
12
#1500
02
#1550
11
b100 F
12
#1600
02
#1650
1&
b1 <
01
b1111110000 !
b1111110000 E
0'
12
#1700
02
#1750
b0 *
b0 8
b1111111111111 +
b1111111111111 A
1D
b0 <
12
#1800
02
#1850
b1111111111111 (
b1111111111111 9
b1111111111111 ,
b1111111111111 7
b101 F
b0 )
b0 B
b0 -
b0 ?
b10 C
b10 @
12
#1900
02
#1950
0&
1'
0G
12
#2000
02
#2050
b1111111111101 ,
b1111111111101 7
b1111111111101 (
b1111111111101 9
b10 F
b10 -
b10 ?
b10 )
b10 B
12
#2100
02
#2150
11
b110 F
12
#2200
02
#2250
b1111111111001 (
b1111111111001 9
b10 F
b11 ;
01
b1111111000 !
b1111111000 E
b110 )
b110 B
b1000010010110 C
12
#2300
02
#2350
11
b110 F
12
#2400
02
#2450
b1111111100001 (
b1111111100001 9
b10 F
b10 ;
01
b1111111100 !
b1111111100 E
b11110 )
b11110 B
b1100011011110 C
12
#2500
02
#2550
11
b110 F
12
#2600
02
#2650
b1111100000001 (
b1111100000001 9
b10 F
b1 ;
01
b1111111110 !
b1111111110 E
b11111110 )
b11111110 B
b1110011111110 C
12
#2700
02
#2750
11
b110 F
12
#2800
02
#2850
b1 (
b1 9
b10 F
b0 ;
01
b1111111111 !
b1111111111 E
b1111111111110 )
b1111111111110 B
b1111111111110 C
12
#2900
02
#2950
11
b110 F
12
#3000
02
#3050
0"
1#
b0 F
10
01
12
#3100
02
#3150
1"
0#
b1111111111111 *
b1111111111111 8
b0 (
b0 9
b1111111111111 .
b1111111111111 6
b0 ,
b0 7
b0 C
b0 @
b0 +
b0 A
b1111111111111 )
b1111111111111 B
b0 /
b0 >
b1111111111111 -
b1111111111111 ?
b1000000000 !
b1000000000 E
1G
b10 =
b100 ;
b100 :
b10 <
00
b1 F
12
#3200
02
#3250
0$
b1 =
1%
12
#3300
02
#3350
1$
0%
b0 =
12
#3400
02
#3450
b11111111 *
b11111111 8
b11111111 .
b11111111 6
b10 F
b1111100000000 +
b1111100000000 A
b1111100000000 /
b1111100000000 >
12
